definitions.v
// ALU Control Codes
`define ALU_ADD  4'b0000
`define ALU_SUB  4'b1000
`define ALU_SLL  4'b0001
`define ALU_SLT  4'b0010
`define ALU_SLTU 4'b0011
`define ALU_XOR  4'b0100
`define ALU_SRL  4'b0101
`define ALU_SRA  4'b1101
`define ALU_OR   4'b0110
`define ALU_AND  4'b0111
`define ALU_LUI  4'b1001 // Pass Immediate B

controller.v
`include "definitions.v"

module controller (
    input  wire [6:0] opcode,
    input  wire [2:0] funct3,
    input  wire [6:0] funct7,
    
    output wire       reg_write,
    output wire       alu_src,    // Selects RegB (0) or Imm (1)
    output wire       mem_write,
    output wire [1:0] result_src, // 00: ALU, 01: Mem, 10: PC+4
    output wire [2:0] imm_src,
    output wire [3:0] alu_control,
    output wire       pc_src,     // Branch decision
    output wire       jump        // Unconditional jump (JAL)
);

    wire [1:0] alu_op;
    wire       branch;

    // Main Decoder
    main_decoder md (
        .opcode(opcode),
        .reg_write(reg_write),
        .imm_src(imm_src),
        .alu_src(alu_src),
        .mem_write(mem_write),
        .result_src(result_src),
        .branch(branch),
        .alu_op(alu_op),
        .jump(jump)
    );

    // ALU Decoder
    alu_decoder ad (
        .alu_op(alu_op),
        .funct3(funct3),
        .funct7(funct7),
        .opcode(opcode),
        .alu_control(alu_control)
    );

    // PC Source Logic for Branching (BEQ)
    // Note: The Zero flag check happens in the top level. 
    // Here we just expose the control signals.
    // However, usually pc_src depends on Zero. 
    // For this module structure, I will export 'branch' and let Top Level combine it with 'Zero'.
    assign pc_src = branch;
    
endmodule

module main_decoder (
    input  wire [6:0] opcode,
    output reg        reg_write,
    output reg  [2:0] imm_src,
    output reg        alu_src,
    output reg        mem_write,
    output reg  [1:0] result_src,
    output reg        branch,
    output reg  [1:0] alu_op,
    output reg        jump
);
    // Opcodes
    localparam OP_R_TYPE = 7'b0110011;
    localparam OP_I_TYPE = 7'b0010011;
    localparam OP_LOAD   = 7'b0000011;
    localparam OP_STORE  = 7'b0100011;
    localparam OP_BRANCH = 7'b1100011; // beq
    localparam OP_JAL    = 7'b1101111; // jal
    localparam OP_LUI    = 7'b0110111; // lui

    always @(*) begin
        // Defaults
        reg_write = 0; imm_src = 0; alu_src = 0; mem_write = 0;
        result_src = 0; branch = 0; alu_op = 0; jump = 0;

        case (opcode)
            OP_R_TYPE: begin // R-Type
                reg_write = 1;
                alu_op    = 2'b10;
            end
            OP_I_TYPE: begin // I-Type ALU
                reg_write = 1;
                alu_src   = 1; // Use Immediate
                alu_op    = 2'b10; // Use funct3/7 to determine op
            end
            OP_LOAD: begin // lw
                reg_write  = 1;
                alu_src    = 1;
                imm_src    = 3'b000;
                result_src = 2'b01; // From Memory
                alu_op     = 2'b00; // ADD
            end
            OP_STORE: begin // sw
                mem_write = 1;
                alu_src   = 1;
                imm_src   = 3'b001; // S-Type
                alu_op    = 2'b00; // ADD
            end
            OP_BRANCH: begin // beq
                branch  = 1;
                alu_op  = 2'b01; // Sub (compare)
                imm_src = 3'b010; // B-Type
            end
            OP_JAL: begin // jal
                jump       = 1;
                reg_write  = 1;
                imm_src    = 3'b011; // J-Type
                result_src = 2'b10;  // PC+4
            end
            OP_LUI: begin // lui
                reg_write = 1;
                alu_src   = 1;
                imm_src   = 3'b100; // U-Type
                alu_op    = 2'b11;  // Pass through
            end
        endcase
    end
endmodule

module alu_decoder (
    input  wire [1:0] alu_op,
    input  wire [2:0] funct3,
    input  wire [6:0] funct7,
    input  wire [6:0] opcode,
    output reg  [3:0] alu_control
);
    always @(*) begin
        case (alu_op)
            2'b00: alu_control = `ALU_ADD; // LW, SW (Add)
            2'b01: alu_control = `ALU_SUB; // BEQ (Sub)
            2'b11: alu_control = `ALU_LUI; // LUI (Pass Imm)
            2'b10: begin // R-Type or I-Type
                case (funct3)
                    3'b000: begin // ADD or SUB
                         if (opcode == 7'b0110011 && funct7[5]) // R-type SUB
                             alu_control = `ALU_SUB;
                         else 
                             alu_control = `ALU_ADD; // ADD or ADDI
                    end
                    3'b001: alu_control = `ALU_SLL; // SLL, SLLI
                    3'b010: alu_control = `ALU_SLT; // SLT, SLTI
                    3'b011: alu_control = `ALU_SLTU; // SLTU, SLTIU
                    3'b100: alu_control = `ALU_XOR; // XOR, XORI
                    3'b101: begin // SRL, SRA
                        if (funct7[5]) alu_control = `ALU_SRA; // SRA, SRAI
                        else           alu_control = `ALU_SRL; // SRL, SRLI
                    end
                    3'b110: alu_control = `ALU_OR;  // OR, ORI
                    3'b111: alu_control = `ALU_AND; // AND, ANDI
                    default: alu_control = `ALU_ADD;
                endcase
            end
        endcase
    end
endmodule

alu.v
`include "definitions.v"

module alu (
    input  wire [31:0] src_a,
    input  wire [31:0] src_b,
    input  wire [3:0]  alu_control,
    output reg  [31:0] alu_result,
    output wire        zero
);
    wire signed [31:0] src_a_signed = src_a;
    
    always @(*) begin
        case (alu_control)
            `ALU_ADD:  alu_result = src_a + src_b;
            `ALU_SUB:  alu_result = src_a - src_b;
            `ALU_AND:  alu_result = src_a & src_b;
            `ALU_OR:   alu_result = src_a | src_b;
            `ALU_XOR:  alu_result = src_a ^ src_b;
            `ALU_SLL:  alu_result = src_a << src_b[4:0];
            `ALU_SRL:  alu_result = src_a >> src_b[4:0];
            `ALU_SRA:  alu_result = src_a_signed >>> src_b[4:0]; // Arithmetic shift
            `ALU_SLT:  alu_result = (src_a_signed < $signed(src_b)) ? 32'd1 : 32'd0;
            `ALU_SLTU: alu_result = (src_a < src_b) ? 32'd1 : 32'd0;
            `ALU_LUI:  alu_result = src_b; // Pass immediate for LUI
            default:   alu_result = 32'b0;
        endcase
    end

    // Zero flag for BEQ
    assign zero = (alu_result == 32'b0);
endmodule

sign_extend.v
module sign_extend (
    input  wire [31:0] instr,
    input  wire [2:0]  imm_src, // Control signal to select type
    output reg  [31:0] imm_ext
);
    always @(*) begin
        case (imm_src)
            // I-Type (lw, I-type ALU, jalr)
            3'b000: imm_ext = {{20{instr[31]}}, instr[31:20]};
            // S-Type (sw)
            3'b001: imm_ext = {{20{instr[31]}}, instr[31:25], instr[11:7]};
            // B-Type (beq)
            3'b010: imm_ext = {{20{instr[31]}}, instr[7], instr[30:25], instr[11:8], 1'b0};
            // J-Type (jal)
            3'b011: imm_ext = {{12{instr[31]}}, instr[19:12], instr[20], instr[30:21], 1'b0};
            // U-Type (lui) - Upper Immediate
            3'b100: imm_ext = {instr[31:12], 12'b0}; 
            default: imm_ext = 32'b0;
        endcase
    end
endmodule

reg_file.v
module reg_file (
    input  wire        clk,
    input  wire        we3,      // Write Enable
    input  wire [4:0]  a1,       // Read Address 1 (rs1)
    input  wire [4:0]  a2,       // Read Address 2 (rs2)
    input  wire [4:0]  a3,       // Write Address (rd)
    input  wire [31:0] wd3,      // Write Data
    output wire [31:0] rd1,      // Read Data 1
    output wire [31:0] rd2       // Read Data 2
);
    reg [31:0] rf [31:0];

    // Combinational Read (x0 is always 0)
    assign rd1 = (a1 != 0) ? rf[a1] : 32'b0;
    assign rd2 = (a2 != 0) ? rf[a2] : 32'b0;

    // Sequential Write
    always @(posedge clk) begin
        if (we3 && a3 != 0) begin
            rf[a3] <= wd3;
        end
    end
endmodule

pc_reg.v
module pc_reg (
    input  wire        clk,
    input  wire        rst_n,
    input  wire [31:0] pc_next,
    output reg  [31:0] pc
);
    // Reset to 0 as per typical simulation start
    always @(posedge clk or negedge rst_n) begin
        if (!rst_n) pc <= 32'b0;
        else        pc <= pc_next;
    end
endmodule

riscv_top.v
`include "definitions.v"
`include "controller.v"
`include "alu.v"
`include "reg_file.v"
`include "pc_reg.v"
`include "sign_extend.v"

module riscv_top (
    input wire clk,
    input wire rst_n
);

    // Wires
    wire [31:0] pc, pc_next, pc_plus4, pc_target;
    wire [31:0] instr;
    wire [31:0] rd1, rd2;
    wire [31:0] imm_ext;
    wire [31:0] src_b;
    wire [31:0] alu_result;
    wire [31:0] read_data; // From Data Memory
    wire [31:0] result;    // Final write back data
    wire        zero;
    
    // Control Signals
    wire        reg_write;
    wire        alu_src;
    wire        mem_write;
    wire [1:0]  result_src;
    wire [2:0]  imm_src;
    wire [3:0]  alu_control;
    wire        branch;
    wire        jump;
    wire        pc_src;

    // ---------------------------------------------
    // Instruction Memory
    // ---------------------------------------------
    // Note: Simulating behavior. In real HW this is often a separate IP block.
    // Address is byte addressed, but we fetch words (align by 4)
    reg [31:0] imem [0:255]; 
    assign instr = imem[pc[9:2]]; 

    // ---------------------------------------------
    // Data Memory
    // ---------------------------------------------
    reg [31:0] dmem [0:255];
    always @(posedge clk) begin
        if (mem_write) dmem[alu_result[9:2]] <= rd2;
    end
    assign read_data = dmem[alu_result[9:2]];

    // ---------------------------------------------
    // Datapath Components
    // ---------------------------------------------
    
    // Program Counter
    pc_reg pcreg (
        .clk(clk),
        .rst_n(rst_n),
        .pc_next(pc_next),
        .pc(pc)
    );

    // PC Adder (PC + 4)
    assign pc_plus4 = pc + 4;

    // Branch Target Adder (PC + Imm)
    assign pc_target = pc + imm_ext;

    // PC Mux Logic (Branching and Jumping)
    // pc_src is true if (Branch taken) OR (Jump)
    assign pc_src = (branch & zero) | jump;
    assign pc_next = (pc_src) ? pc_target : pc_plus4;

    // Register File
    reg_file rf (
        .clk(clk),
        .we3(reg_write),
        .a1(instr[19:15]),
        .a2(instr[24:20]),
        .a3(instr[11:7]),
        .wd3(result),
        .rd1(rd1),
        .rd2(rd2)
    );

    // Sign Extender
    sign_extend ext (
        .instr(instr),
        .imm_src(imm_src),
        .imm_ext(imm_ext)
    );

    // ALU Source Mux 
    assign src_b = (alu_src) ? imm_ext : rd2;

    // ALU
    alu alu_unit (
        .src_a(rd1),
        .src_b(src_b),
        .alu_control(alu_control),
        .alu_result(alu_result),
        .zero(zero)
    );

    // Result Mux (Write Back)
    // Selects between ALU Result, Data Memory, or PC+4 (for JAL)
    assign result = (result_src == 2'b00) ? alu_result :
                    (result_src == 2'b01) ? read_data :
                    (result_src == 2'b10) ? pc_plus4 : 32'b0;

    // ---------------------------------------------
    // Controller
    // ---------------------------------------------
    controller c (
        .opcode(instr[6:0]),
        .funct3(instr[14:12]),
        .funct7(instr[31:25]),
        .reg_write(reg_write),
        .alu_src(alu_src),
        .mem_write(mem_write),
        .result_src(result_src),
        .imm_src(imm_src),
        .alu_control(alu_control),
        .pc_src(branch),
        .jump(jump)
    );
endmodule

tb.v
`timescale 1ns / 1ps
`include "riscv_top.v"

module tb_riscv();

    reg clk;
    reg rst_n;
    wire [31:0] test_pc;
    wire [31:0] test_instr;

    // 1. Instantiate the Device Under Test
    riscv_top dut (
        .clk(clk),
        .rst_n(rst_n)
    );

    // 2. Generate Clock (10ns period)
    always #5 clk = ~clk;

    // 3. Simulation Control
    initial begin
        // Initialize Signals
        clk = 0;
        rst_n = 0;

        // Initialize Instruction Memory from Hex file
        $readmemh("test.hex", dut.imem);

        // Reset Sequence
        #20;
        rst_n = 1;  // Release reset
        
        // Run simulation for enough time to complete the program
        #5000;
        
        $display("-------------------------------------------------------------");
        $display("Verification Report (Updated Test)");
        $display("-------------------------------------------------------------");
        $display("Register File Content:");
        $display("x1 (Base Addr): %h (Expected: 10000000)", dut.rf.rf[1]);
        $display("x2 (10):        %h (Expected: 0000000a)", dut.rf.rf[2]);
        $display("x3 (-5):        %h (Expected: fffffffb)", dut.rf.rf[3]);
        $display("x4 (ADDI):      %h (Expected: 0000001e)", dut.rf.rf[4]);
        $display("x5 (XORI):      %h (Expected: fffffff5)", dut.rf.rf[5]);
        $display("x6 (ANDI):      %h (Expected: 00000005)", dut.rf.rf[6]);
        $display("x7 (ORI):       %h (Expected: 00000015)", dut.rf.rf[7]);
        $display("x8 (SLLI):      %h (Expected: 00000028)", dut.rf.rf[8]);
        $display("x9 (SRLI):      %h (Expected: 3ffffffe)", dut.rf.rf[9]);
        $display("x10 (SRAI):     %h (Expected: fffffffe)", dut.rf.rf[10]);
        $display("x11 (SLTI):     %h (Expected: 00000001)", dut.rf.rf[11]);
        $display("x12 (SLTIU):    %h (Expected: 00000000)", dut.rf.rf[12]);
        $display("x13 (ADD):      %h (Expected: 00000005)", dut.rf.rf[13]);
        $display("x14 (SUB):      %h (Expected: 0000000f)", dut.rf.rf[14]);
        $display("x15 (AND):      %h (Expected: 0000000a)", dut.rf.rf[15]);
        $display("x16 (OR):       %h (Expected: fffffffb)", dut.rf.rf[16]);
        $display("x17 (XOR):      %h (Expected: fffffff1)", dut.rf.rf[17]);
        $display("x18 (1):        %h (Expected: 00000001)", dut.rf.rf[18]);
        $display("x19 (SLL):      %h (Expected: 00000014)", dut.rf.rf[19]);
        $display("x20 (SRL):      %h (Expected: 7ffffffd)", dut.rf.rf[20]);
        $display("x21 (SRA):      %h (Expected: fffffffd)", dut.rf.rf[21]);
        $display("x22 (SLT):      %h (Expected: 00000001)", dut.rf.rf[22]);
        $display("x23 (SLTU):     %h (Expected: 00000000)", dut.rf.rf[23]);
        $display("x24 (LW):       %h (Expected: 00000001)", dut.rf.rf[24]);
        $display("x25 (PASS):     %h (Expected: 00000001)", dut.rf.rf[25]);
        $display("-------------------------------------------------------------");

        $display("Simulation finished.");
        $finish;
    end

    // 4. Monitoring 
    initial begin
        $monitor("Time: %t | PC: %h | Instr: %h | Result: %h | RegWrite: %b", 
                 $time, dut.pc, dut.instr, dut.result, dut.reg_write);
    end

    // 5. Waveform Dump
    initial begin
        $dumpfile("riscv_wave.vcd");
        $dumpvars(0, tb_riscv);
        // Dump the registers specifically to see data changes
        for (integer i = 0; i < 32; i = i + 1) begin
            $dumpvars(0, dut.rf.rf[i]);
        end
    end

endmodule

riscv_wave.vcd
$date
	Fri Dec  5 22:41:48 2025
$end
$version
	Icarus Verilog
$end
$timescale
	1ps
$end
$scope module tb_riscv $end
$var reg 1 ! clk $end
$var reg 1 " rst_n $end
$scope module dut $end
$var wire 1 ! clk $end
$var wire 32 # instr [31:0] $end
$var wire 1 $ pc_src $end
$var wire 32 % read_data [31:0] $end
$var wire 1 " rst_n $end
$var wire 1 & zero $end
$var wire 32 ' src_b [31:0] $end
$var wire 2 ( result_src [1:0] $end
$var wire 32 ) result [31:0] $end
$var wire 1 * reg_write $end
$var wire 32 + rd2 [31:0] $end
$var wire 32 , rd1 [31:0] $end
$var wire 32 - pc_target [31:0] $end
$var wire 32 . pc_plus4 [31:0] $end
$var wire 32 / pc_next [31:0] $end
$var wire 32 0 pc [31:0] $end
$var wire 1 1 mem_write $end
$var wire 1 2 jump $end
$var wire 3 3 imm_src [2:0] $end
$var wire 32 4 imm_ext [31:0] $end
$var wire 1 5 branch $end
$var wire 1 6 alu_src $end
$var wire 32 7 alu_result [31:0] $end
$var wire 4 8 alu_control [3:0] $end
$scope module alu_unit $end
$var wire 32 9 src_a_signed [31:0] $end
$var wire 32 : src_b [31:0] $end
$var wire 1 & zero $end
$var wire 32 ; src_a [31:0] $end
$var wire 4 < alu_control [3:0] $end
$var reg 32 = alu_result [31:0] $end
$upscope $end
$scope module c $end
$var wire 3 > funct3 [2:0] $end
$var wire 7 ? funct7 [6:0] $end
$var wire 7 @ opcode [6:0] $end
$var wire 1 5 pc_src $end
$var wire 2 A result_src [1:0] $end
$var wire 1 * reg_write $end
$var wire 1 1 mem_write $end
$var wire 1 2 jump $end
$var wire 3 B imm_src [2:0] $end
$var wire 1 C branch $end
$var wire 1 6 alu_src $end
$var wire 2 D alu_op [1:0] $end
$var wire 4 E alu_control [3:0] $end
$scope module ad $end
$var wire 3 F funct3 [2:0] $end
$var wire 7 G funct7 [6:0] $end
$var wire 7 H opcode [6:0] $end
$var wire 2 I alu_op [1:0] $end
$var reg 4 J alu_control [3:0] $end
$upscope $end
$scope module md $end
$var wire 7 K opcode [6:0] $end
$var reg 2 L alu_op [1:0] $end
$var reg 1 6 alu_src $end
$var reg 1 C branch $end
$var reg 3 M imm_src [2:0] $end
$var reg 1 2 jump $end
$var reg 1 1 mem_write $end
$var reg 1 * reg_write $end
$var reg 2 N result_src [1:0] $end
$upscope $end
$upscope $end
$scope module ext $end
$var wire 3 O imm_src [2:0] $end
$var wire 32 P instr [31:0] $end
$var reg 32 Q imm_ext [31:0] $end
$upscope $end
$scope module pcreg $end
$var wire 1 ! clk $end
$var wire 32 R pc_next [31:0] $end
$var wire 1 " rst_n $end
$var reg 32 S pc [31:0] $end
$upscope $end
$scope module rf $end
$var wire 5 T a1 [4:0] $end
$var wire 5 U a2 [4:0] $end
$var wire 5 V a3 [4:0] $end
$var wire 1 ! clk $end
$var wire 32 W wd3 [31:0] $end
$var wire 1 * we3 $end
$var wire 32 X rd2 [31:0] $end
$var wire 32 Y rd1 [31:0] $end
$upscope $end
$upscope $end
$scope begin $ivl_for_loop0 $end
$var integer 32 Z i [31:0] $end
$upscope $end
$upscope $end
$scope module tb_riscv $end
$scope module dut $end
$scope module rf $end
$var reg 32 [ \rf[0] [31:0] $end
$upscope $end
$upscope $end
$upscope $end
$scope module tb_riscv $end
$scope module dut $end
$scope module rf $end
$var reg 32 \ \rf[1] [31:0] $end
$upscope $end
$upscope $end
$upscope $end
$scope module tb_riscv $end
$scope module dut $end
$scope module rf $end
$var reg 32 ] \rf[2] [31:0] $end
$upscope $end
$upscope $end
$upscope $end
$scope module tb_riscv $end
$scope module dut $end
$scope module rf $end
$var reg 32 ^ \rf[3] [31:0] $end
$upscope $end
$upscope $end
$upscope $end
$scope module tb_riscv $end
$scope module dut $end
$scope module rf $end
$var reg 32 _ \rf[4] [31:0] $end
$upscope $end
$upscope $end
$upscope $end
$scope module tb_riscv $end
$scope module dut $end
$scope module rf $end
$var reg 32 ` \rf[5] [31:0] $end
$upscope $end
$upscope $end
$upscope $end
$scope module tb_riscv $end
$scope module dut $end
$scope module rf $end
$var reg 32 a \rf[6] [31:0] $end
$upscope $end
$upscope $end
$upscope $end
$scope module tb_riscv $end
$scope module dut $end
$scope module rf $end
$var reg 32 b \rf[7] [31:0] $end
$upscope $end
$upscope $end
$upscope $end
$scope module tb_riscv $end
$scope module dut $end
$scope module rf $end
$var reg 32 c \rf[8] [31:0] $end
$upscope $end
$upscope $end
$upscope $end
$scope module tb_riscv $end
$scope module dut $end
$scope module rf $end
$var reg 32 d \rf[9] [31:0] $end
$upscope $end
$upscope $end
$upscope $end
$scope module tb_riscv $end
$scope module dut $end
$scope module rf $end
$var reg 32 e \rf[10] [31:0] $end
$upscope $end
$upscope $end
$upscope $end
$scope module tb_riscv $end
$scope module dut $end
$scope module rf $end
$var reg 32 f \rf[11] [31:0] $end
$upscope $end
$upscope $end
$upscope $end
$scope module tb_riscv $end
$scope module dut $end
$scope module rf $end
$var reg 32 g \rf[12] [31:0] $end
$upscope $end
$upscope $end
$upscope $end
$scope module tb_riscv $end
$scope module dut $end
$scope module rf $end
$var reg 32 h \rf[13] [31:0] $end
$upscope $end
$upscope $end
$upscope $end
$scope module tb_riscv $end
$scope module dut $end
$scope module rf $end
$var reg 32 i \rf[14] [31:0] $end
$upscope $end
$upscope $end
$upscope $end
$scope module tb_riscv $end
$scope module dut $end
$scope module rf $end
$var reg 32 j \rf[15] [31:0] $end
$upscope $end
$upscope $end
$upscope $end
$scope module tb_riscv $end
$scope module dut $end
$scope module rf $end
$var reg 32 k \rf[16] [31:0] $end
$upscope $end
$upscope $end
$upscope $end
$scope module tb_riscv $end
$scope module dut $end
$scope module rf $end
$var reg 32 l \rf[17] [31:0] $end
$upscope $end
$upscope $end
$upscope $end
$scope module tb_riscv $end
$scope module dut $end
$scope module rf $end
$var reg 32 m \rf[18] [31:0] $end
$upscope $end
$upscope $end
$upscope $end
$scope module tb_riscv $end
$scope module dut $end
$scope module rf $end
$var reg 32 n \rf[19] [31:0] $end
$upscope $end
$upscope $end
$upscope $end
$scope module tb_riscv $end
$scope module dut $end
$scope module rf $end
$var reg 32 o \rf[20] [31:0] $end
$upscope $end
$upscope $end
$upscope $end
$scope module tb_riscv $end
$scope module dut $end
$scope module rf $end
$var reg 32 p \rf[21] [31:0] $end
$upscope $end
$upscope $end
$upscope $end
$scope module tb_riscv $end
$scope module dut $end
$scope module rf $end
$var reg 32 q \rf[22] [31:0] $end
$upscope $end
$upscope $end
$upscope $end
$scope module tb_riscv $end
$scope module dut $end
$scope module rf $end
$var reg 32 r \rf[23] [31:0] $end
$upscope $end
$upscope $end
$upscope $end
$scope module tb_riscv $end
$scope module dut $end
$scope module rf $end
$var reg 32 s \rf[24] [31:0] $end
$upscope $end
$upscope $end
$upscope $end
$scope module tb_riscv $end
$scope module dut $end
$scope module rf $end
$var reg 32 t \rf[25] [31:0] $end
$upscope $end
$upscope $end
$upscope $end
$scope module tb_riscv $end
$scope module dut $end
$scope module rf $end
$var reg 32 u \rf[26] [31:0] $end
$upscope $end
$upscope $end
$upscope $end
$scope module tb_riscv $end
$scope module dut $end
$scope module rf $end
$var reg 32 v \rf[27] [31:0] $end
$upscope $end
$upscope $end
$upscope $end
$scope module tb_riscv $end
$scope module dut $end
$scope module rf $end
$var reg 32 w \rf[28] [31:0] $end
$upscope $end
$upscope $end
$upscope $end
$scope module tb_riscv $end
$scope module dut $end
$scope module rf $end
$var reg 32 x \rf[29] [31:0] $end
$upscope $end
$upscope $end
$upscope $end
$scope module tb_riscv $end
$scope module dut $end
$scope module rf $end
$var reg 32 y \rf[30] [31:0] $end
$upscope $end
$upscope $end
$upscope $end
$scope module tb_riscv $end
$scope module dut $end
$scope module rf $end
$var reg 32 z \rf[31] [31:0] $end
$upscope $end
$upscope $end
$upscope $end
$enddefinitions $end
#0
$dumpvars
bx z
bx y
bx x
bx w
bx v
bx u
bx t
bx s
bx r
bx q
bx p
bx o
bx n
bx m
bx l
bx k
bx j
bx i
bx h
bx g
bx f
bx e
bx d
bx c
bx b
bx a
bx `
bx _
bx ^
bx ]
bx \
bx [
b100000 Z
b0 Y
b0 X
b10000000000000000000000000000 W
b1 V
b0 U
b0 T
b0 S
b100 R
b10000000000000000000000000000 Q
b10000000000000000000010110111 P
b100 O
b0 N
b100 M
b11 L
b110111 K
b1001 J
b11 I
b110111 H
b1000 G
b0 F
b1001 E
b11 D
0C
b100 B
b0 A
b110111 @
b1000 ?
b0 >
b10000000000000000000000000000 =
b1001 <
b0 ;
b10000000000000000000000000000 :
b0 9
b1001 8
b10000000000000000000000000000 7
16
05
b10000000000000000000000000000 4
b100 3
02
01
b0 0
b100 /
b100 .
b10000000000000000000000000000 -
b0 ,
b0 +
1*
b10000000000000000000000000000 )
b0 (
b10000000000000000000000000000 '
0&
bx %
0$
b10000000000000000000010110111 #
0"
0!
$end
#5000
b10000000000000000000000000000 \
1!
#10000
0!
#15000
b10000000000000000000000000000 \
1!
#20000
0!
1"
#25000
b1010 )
b1010 W
b0 8
b0 <
b0 E
b0 J
b1010 7
b1010 =
bx +
bx X
b10 D
b10 I
b10 L
16
b0 3
b0 B
b0 M
b0 O
1*
b1010 '
b1010 :
b1010 U
b10 V
b10011 @
b10011 H
b10011 K
b0 ?
b0 G
b1010 4
b1010 Q
b1000 /
b1000 R
b101000000000000100010011 #
b101000000000000100010011 P
b1110 -
b1000 .
b100 0
b100 S
b10000000000000000000000000000 \
1!
#30000
0!
#35000
b11111111111111111111111111111011 )
b11111111111111111111111111111011 W
b11111111111111111111111111111011 7
b11111111111111111111111111111011 =
b11111111111111111111111111111011 '
b11111111111111111111111111111011 :
b11011 U
b11 V
b1111111 ?
b1111111 G
b11111111111111111111111111111011 4
b11111111111111111111111111111011 Q
b1100 /
b1100 R
b11111111101100000000000110010011 #
b11111111101100000000000110010011 P
b11 -
b1100 .
b1000 0
b1000 S
b1010 ]
1!
#40000
0!
#45000
b11110 )
b11110 W
b11110 7
b11110 =
b1010 9
b1010 ,
b1010 ;
b1010 Y
b10100 '
b10100 :
b10 T
b10100 U
b100 V
b0 ?
b0 G
b10100 4
b10100 Q
b10000 /
b10000 R
b1010000010000001000010011 #
b1010000010000001000010011 P
b100000 -
b10000 .
b1100 0
b1100 S
b11111111111111111111111111111011 ^
1!
#50000
0!
#55000
b11111111111111111111111111110101 )
b11111111111111111111111111110101 W
b11111111111111111111111111110101 7
b11111111111111111111111111110101 =
b100 8
b100 <
b100 E
b100 J
b11111111111111111111111111111111 '
b11111111111111111111111111111111 :
b11111 U
b101 V
b100 >
b100 F
b1111111 ?
b1111111 G
b11111111111111111111111111111111 4
b11111111111111111111111111111111 Q
b10100 /
b10100 R
b11111111111100010100001010010011 #
b11111111111100010100001010010011 P
b1111 -
b10100 .
b10000 0
b10000 S
b11110 _
1!
#60000
0!
#65000
b101 )
b101 W
b101 7
b101 =
b11111111111111111111111111110101 9
b11111111111111111111111111110101 ,
b11111111111111111111111111110101 ;
b11111111111111111111111111110101 Y
b111 8
b111 <
b111 E
b111 J
b1111 '
b1111 :
b101 T
b1111 U
b110 V
b111 >
b111 F
b0 ?
b0 G
b1111 4
b1111 Q
b11000 /
b11000 R
b111100101111001100010011 #
b111100101111001100010011 P
b100011 -
b11000 .
b10100 0
b10100 S
b11111111111111111111111111110101 `
1!
#70000
0!
#75000
b10101 )
b10101 W
b10101 7
b10101 =
b101 9
b101 ,
b101 ;
b101 Y
b110 8
b110 <
b110 E
b110 J
b10000 '
b10000 :
b110 T
b10000 U
b111 V
b110 >
b110 F
b10000 4
b10000 Q
b11100 /
b11100 R
b1000000110110001110010011 #
b1000000110110001110010011 P
b101000 -
b11100 .
b11000 0
b11000 S
b101 a
1!
#80000
0!
#85000
b101000 )
b101000 W
b101000 7
b101000 =
b1010 9
b1010 ,
b1010 ;
b1010 Y
b1010 +
b1010 X
b1 8
b1 <
b1 E
b1 J
b10 '
b10 :
b10 T
b10 U
b1000 V
b1 >
b1 F
b10 4
b10 Q
b100000 /
b100000 R
b1000010001010000010011 #
b1000010001010000010011 P
b11110 -
b100000 .
b11100 0
b11100 S
b10101 b
1!
#90000
0!
#95000
b111111111111111111111111111110 )
b111111111111111111111111111110 W
b111111111111111111111111111110 7
b111111111111111111111111111110 =
b11111111111111111111111111111011 9
b11111111111111111111111111111011 ,
b11111111111111111111111111111011 ;
b11111111111111111111111111111011 Y
b101 8
b101 <
b101 E
b101 J
b11 T
b1001 V
b101 >
b101 F
b100100 /
b100100 R
b1000011101010010010011 #
b1000011101010010010011 P
b100010 -
b100100 .
b100000 0
b100000 S
b101000 c
1!
#100000
0!
#105000
b11111111111111111111111111111110 )
b11111111111111111111111111111110 W
b11111111111111111111111111111110 7
b11111111111111111111111111111110 =
b1101 8
b1101 <
b1101 E
b1101 J
b10000000010 '
b10000000010 :
b1010 V
b100000 ?
b100000 G
b10000000010 4
b10000000010 Q
b101000 /
b101000 R
b1000000001000011101010100010011 #
b1000000001000011101010100010011 P
b10000100110 -
b101000 .
b100100 0
b100100 S
b111111111111111111111111111110 d
1!
#110000
0!
#115000
b1 )
b1 W
b1 7
b1 =
b11111111111111111111111111111110 +
b11111111111111111111111111111110 X
b10 8
b10 <
b10 E
b10 J
b1010 '
b1010 :
b1010 U
b1011 V
b10 >
b10 F
b0 ?
b0 G
b1010 4
b1010 Q
b101100 /
b101100 R
b101000011010010110010011 #
b101000011010010110010011 P
b110010 -
b101100 .
b101000 0
b101000 S
b11111111111111111111111111111110 e
1!
#120000
0!
#125000
b0 )
b0 W
1&
b0 7
b0 =
b11 8
b11 <
b11 E
b11 J
b1100 V
b11 >
b11 F
b110000 /
b110000 R
b101000011011011000010011 #
b101000011011011000010011 P
b110110 -
b110000 .
b101100 0
b101100 S
b1 f
1!
#130000
0!
#135000
b101 )
b101 W
0&
b101 7
b101 =
b1010 9
b1010 ,
b1010 ;
b1010 Y
b11111111111111111111111111111011 +
b11111111111111111111111111111011 X
b10 D
b10 I
b10 L
06
1*
b0 8
b0 <
b0 E
b0 J
b11111111111111111111111111111011 '
b11111111111111111111111111111011 :
b10 T
b11 U
b1101 V
b110011 @
b110011 H
b110011 K
b0 >
b0 F
b11 4
b11 Q
b110100 /
b110100 R
b1100010000011010110011 #
b1100010000011010110011 P
b110011 -
b110100 .
b110000 0
b110000 S
b0 g
1!
#140000
0!
#145000
b1111 )
b1111 W
b1111 7
b1111 =
b1000 8
b1000 <
b1000 E
b1000 J
b1110 V
b100000 ?
b100000 G
b10000000011 4
b10000000011 Q
b111000 /
b111000 R
b1000000001100010000011100110011 #
b1000000001100010000011100110011 P
b10000110111 -
b111000 .
b110100 0
b110100 S
b101 h
1!
#150000
0!
#155000
b1010 )
b1010 W
b1010 7
b1010 =
b111 8
b111 <
b111 E
b111 J
b1111 V
b111 >
b111 F
b0 ?
b0 G
b11 4
b11 Q
b111100 /
b111100 R
b1100010111011110110011 #
b1100010111011110110011 P
b111011 -
b111100 .
b111000 0
b111000 S
b1111 i
1!
#160000
0!
#165000
b11111111111111111111111111111011 )
b11111111111111111111111111111011 W
b11111111111111111111111111111011 7
b11111111111111111111111111111011 =
b110 8
b110 <
b110 E
b110 J
b10000 V
b110 >
b110 F
b1000000 /
b1000000 R
b1100010110100000110011 #
b1100010110100000110011 P
b111111 -
b1000000 .
b111100 0
b111100 S
b1010 j
1!
#170000
0!
#175000
b11111111111111111111111111110001 )
b11111111111111111111111111110001 W
b11111111111111111111111111110001 7
b11111111111111111111111111110001 =
b100 8
b100 <
b100 E
b100 J
b10001 V
b100 >
b100 F
b1000100 /
b1000100 R
b1100010100100010110011 #
b1100010100100010110011 P
b1000011 -
b1000100 .
b1000000 0
b1000000 S
b11111111111111111111111111111011 k
1!
#180000
0!
