rv_pl.v
// =============================================================================
// Top-Level Module: rv_pl
// =============================================================================
module rv_pl(
    input clk,
    input rst_n
);

    // =========================================================================
    // Internal Wires & Pipeline Signals
    // =========================================================================

    // --- IF Stage Signals ---
    wire [31:0] F_PC, F_PC_next, F_PC_plus_4, F_instr;
    wire        PC_en;  // From Hazard Unit

    // --- IF/ID Pipeline Register (PLR1) Outputs ---
    reg [31:0] D_PC, D_instr, D_PC_plus_4;
    wire       D_stall, D_flush; 

    // --- ID Stage Signals ---
    wire [31:0] D_imm, D_rs1_data, D_rs2_data;
    wire [4:0]  D_rs1, D_rs2, D_rd;
    wire [2:0]  D_funct3;
    wire [6:0]  D_funct7, D_opcode;
    
    // Control Signals (ID)
    wire       D_regwrite, D_memwrite, D_memread, D_branch, D_alusrc, D_memtoreg, D_jump, D_lui;
    wire [3:0] D_alucontrol;

    // --- ID/EX Pipeline Register (PLR2) Outputs ---
    reg [31:0] E_PC, E_rs1_data, E_rs2_data, E_imm, E_PC_plus_4;
    reg [4:0]  E_rs1, E_rs2, E_rd;
    reg [3:0]  E_alucontrol;
    reg        E_regwrite, E_memwrite, E_memread, E_branch, E_alusrc, E_memtoreg, E_jump, E_lui;
    wire       E_flush; 

    // --- EX Stage Signals ---
    wire [31:0] E_alu_res, E_op1, E_op2, E_target_PC;
    wire [31:0] E_forwarded_rs1, E_forwarded_rs2; 
    wire        E_zero;
    wire        E_branch_taken;
    wire [1:0]  ForwardA, ForwardB; 

    // --- EX/MA Pipeline Register (PLR3) Outputs ---
    reg [31:0] M_alu_res, M_rs2_data, M_PC_plus_4;
    reg [4:0]  M_rd;
    reg        M_regwrite, M_memwrite, M_memread, M_memtoreg, M_jump;

    // --- MA Stage Signals ---
    wire [31:0] M_mem_data;

    // --- MA/WB Pipeline Register (PLR4) Outputs ---
    reg [31:0] W_mem_data, W_alu_res, W_PC_plus_4;
    reg [4:0]  W_rd;
    reg        W_regwrite, W_memtoreg, W_jump;

    // --- WB Stage Signals ---
    wire [31:0] W_result;

    // =========================================================================
    // 1. Instruction Fetch (IF) Stage
    // =========================================================================

    // PC Register (Synchronous Reset) 
    reg [31:0] PC;
    always @(posedge clk) begin
        if (!rst_n) 
            PC <= 32'b0;
        else if (PC_en) 
            PC <= F_PC_next;
    end

    assign F_PC = PC;
    assign F_PC_plus_4 = F_PC + 4;
    
    // PC Mux 
    // Branch taken or Jump taken (calculated in EX stage)
    assign F_PC_next = (E_branch_taken) ? E_target_PC : F_PC_plus_4;

    // Instruction Memory Instance
    instruction_memory IMEM (
        .addr(F_PC),
        .instr(F_instr)
    );

    // =========================================================================
    // IF/ID Pipeline Register (PLR1)
    // =========================================================================
    always @(posedge clk) begin
        if (!rst_n) begin
            D_PC <= 0;
            D_instr <= 0;
            D_PC_plus_4 <= 0;
        end else if (D_flush) begin 
            D_PC <= 0;
            D_instr <= 0; // NOP
            D_PC_plus_4 <= 0;
        end else if (!D_stall) begin 
            D_PC <= F_PC;
            D_instr <= F_instr;
            D_PC_plus_4 <= F_PC_plus_4;
        end
    end

    // =========================================================================
    // 2. Instruction Decode (ID) Stage
    // =========================================================================

    assign D_opcode = D_instr[6:0];
    assign D_rd     = D_instr[11:7];
    assign D_funct3 = D_instr[14:12];
    assign D_rs1    = D_instr[19:15];
    assign D_rs2    = D_instr[24:20];
    assign D_funct7 = D_instr[31:25];

    // Controller
    control_unit CTRL (
        .opcode(D_opcode),
        .funct3(D_funct3),
        .funct7(D_funct7),
        .regwrite(D_regwrite),
        .memwrite(D_memwrite),
        .memread(D_memread),
        .branch(D_branch),
        .alusrc(D_alusrc),
        .memtoreg(D_memtoreg),
        .alucontrol(D_alucontrol),
        .jump(D_jump),
        .lui(D_lui)
    );

    // Register File Instance
    register_file RF (
        .clk(clk),
        .rst_n(rst_n),
        .ra1(D_rs1),
        .ra2(D_rs2),
        .wa(W_rd),
        .wd(W_result),
        .we(W_regwrite),
        .rd1(D_rs1_data),
        .rd2(D_rs2_data)
    );

    // Immediate Generator
    imm_gen EXT (
        .instr(D_instr),
        .imm_out(D_imm)
    );

    // =========================================================================
    // ID/EX Pipeline Register (PLR2)
    // =========================================================================
    always @(posedge clk) begin
        if (!rst_n) begin
            E_PC <= 0; E_rs1_data <= 0; E_rs2_data <= 0; E_imm <= 0; E_PC_plus_4 <= 0;
            E_rs1 <= 0; E_rs2 <= 0; E_rd <= 0; E_alucontrol <= 0;
            E_regwrite <= 0; E_memwrite <= 0; E_memread <= 0; 
            E_branch <= 0; E_alusrc <= 0; E_memtoreg <= 0; E_jump <= 0; E_lui <= 0;
        end else if (E_flush) begin
            E_regwrite <= 0; E_memwrite <= 0; E_memread <= 0; E_branch <= 0; E_jump <= 0;
            E_PC <= 0; E_rd <= 0; // Clear datapath elements relevant to hazards
        end else begin
            E_PC <= D_PC;
            E_rs1_data <= D_rs1_data;
            E_rs2_data <= D_rs2_data;
            E_imm <= D_imm;
            E_PC_plus_4 <= D_PC_plus_4;
            E_rs1 <= D_rs1;
            E_rs2 <= D_rs2;
            E_rd <= D_rd;
            E_alucontrol <= D_alucontrol;
            E_regwrite <= D_regwrite;
            E_memwrite <= D_memwrite;
            E_memread <= D_memread;
            E_branch <= D_branch;
            E_alusrc <= D_alusrc;
            E_memtoreg <= D_memtoreg;
            E_jump <= D_jump;
            E_lui <= D_lui;
        end
    end

    // =========================================================================
    // 3. Execution (EX) Stage
    // =========================================================================

    // Forwarding MUX A
    assign E_forwarded_rs1 = (ForwardA == 2'b10) ? M_alu_res :
                             (ForwardA == 2'b01) ? W_result :
                             E_rs1_data;

    // Forwarding MUX B
    assign E_forwarded_rs2 = (ForwardB == 2'b10) ? M_alu_res :
                             (ForwardB == 2'b01) ? W_result :
                             E_rs2_data;

    // ALU Source Selection
    // LUI Logic: If LUI is active, we ignore rs1 (treat as 0) or simply pass Imm through ALU.
    // The ALU Control 'PASS_B' (4'b1011) handles LUI by passing src_b.
    assign E_op1 = E_forwarded_rs1;
    assign E_op2 = (E_alusrc) ? E_imm : E_forwarded_rs2;

    // ALU
    alu ALU_UNIT (
        .src_a(E_op1),
        .src_b(E_op2),
        .alu_control(E_alucontrol),
        .alu_result(E_alu_res),
        .zero(E_zero)
    );

    // Branch/Jump Logic
    // Branch taken if (Branch & Zero) OR Unconditional Jump
    // For BEQ: taken if zero==1.
    // Note: If you need BNE, BLT etc., you need more branch logic. 
    // The prompt only lists "beq", "jal".
    assign E_branch_taken = (E_branch & E_zero) | E_jump; 
    assign E_target_PC = E_PC + E_imm;

    // =========================================================================
    // EX/MA Pipeline Register (PLR3)
    // =========================================================================
    always @(posedge clk) begin
        if (!rst_n) begin
            M_alu_res <= 0; M_rs2_data <= 0; M_rd <= 0; M_PC_plus_4 <= 0;
            M_regwrite <= 0; M_memwrite <= 0; M_memread <= 0; M_memtoreg <= 0; M_jump <= 0;
        end else begin
            M_alu_res <= E_alu_res;
            M_rs2_data <= E_forwarded_rs2; 
            M_rd <= E_rd;
            M_PC_plus_4 <= E_PC_plus_4;
            M_regwrite <= E_regwrite;
            M_memwrite <= E_memwrite;
            M_memread <= E_memread;
            M_memtoreg <= E_memtoreg;
            M_jump <= E_jump;
        end
    end

    // =========================================================================
    // 4. Memory Access (MA) Stage
    // =========================================================================

    // Data Memory Instance
    data_memory DMEM (
        .clk(clk),
        .addr(M_alu_res),
        .write_data(M_rs2_data),
        .mem_write(M_memwrite),
        .read_data(M_mem_data)
    );

    // =========================================================================
    // MA/WB Pipeline Register (PLR4)
    // =========================================================================
    always @(posedge clk) begin
        if (!rst_n) begin
            W_mem_data <= 0; W_alu_res <= 0; W_rd <= 0; W_PC_plus_4 <= 0;
            W_regwrite <= 0; W_memtoreg <= 0; W_jump <= 0;
        end else begin
            W_mem_data <= M_mem_data;
            W_alu_res <= M_alu_res;
            W_rd <= M_rd;
            W_PC_plus_4 <= M_PC_plus_4;
            W_regwrite <= M_regwrite;
            W_memtoreg <= M_memtoreg;
            W_jump <= M_jump;
        end
    end

    // =========================================================================
    // 5. Write Back (WB) Stage
    // =========================================================================

    // Mux supporting Mem, ALU, and Link Address (PC+4 for JAL)
    assign W_result = (W_jump)     ? W_PC_plus_4 : 
                      (W_memtoreg) ? W_mem_data : 
                                     W_alu_res;


    // =========================================================================
    // Hazard Handling Units
    // =========================================================================

    hazard_detection_unit HAZARD (
        .D_rs1(D_rs1),
        .D_rs2(D_rs2),
        .E_rd(E_rd),
        .E_memread(E_memread),
        .E_branch_taken(E_branch_taken),
        .PC_en(PC_en),      
        .D_stall(D_stall),   
        .D_flush(D_flush),   
        .E_flush(E_flush)    
    );

    forwarding_unit FWD (
        .E_rs1(E_rs1),
        .E_rs2(E_rs2),
        .M_rd(M_rd),
        .M_regwrite(M_regwrite),
        .W_rd(W_rd),
        .W_regwrite(W_regwrite),
        .ForwardA(ForwardA),
        .ForwardB(ForwardB)
    );

endmodule


// =============================================================================
// Module: Hazard Detection Unit
// =============================================================================
module hazard_detection_unit(
    input [4:0] D_rs1, D_rs2,
    input [4:0] E_rd,
    input       E_memread,
    input       E_branch_taken, // Includes Jump
    
    output reg  PC_en,
    output reg  D_stall,
    output reg  D_flush,
    output reg  E_flush
);
    always @(*) begin
        // Defaults
        PC_en = 1'b1;
        D_stall = 1'b0;
        D_flush = 1'b0;
        E_flush = 1'b0;

        // 1. Control Hazard (Branch/Jump Taken)
        // Flushes pipeline when branch is taken or JAL executes
        if (E_branch_taken) begin
            D_flush = 1'b1; // Flush IF/ID
            E_flush = 1'b1; // Flush ID/EX
        end
        // 2. Load-Use Hazard
        // If instruction in EX is Load and destination matches Source in ID
        else if (E_memread && (E_rd != 0) && ((E_rd == D_rs1) || (E_rd == D_rs2))) begin
            PC_en = 1'b0;   // Stall PC
            D_stall = 1'b1; // Stall IF/ID
            E_flush = 1'b1; // Flush ID/EX (bubble)
        end
    end
endmodule


// =============================================================================
// Module: Forwarding Unit
// =============================================================================
module forwarding_unit(
    input [4:0] E_rs1, E_rs2,
    input [4:0] M_rd, W_rd,
    input       M_regwrite, W_regwrite,
    output reg [1:0] ForwardA, ForwardB
);
    always @(*) begin
        ForwardA = 2'b00;
        ForwardB = 2'b00;

        // EX Hazard (Forward from MA stage)
        if (M_regwrite && (M_rd != 0) && (M_rd == E_rs1))
            ForwardA = 2'b10;
        // MEM Hazard (Forward from WB stage)
        else if (W_regwrite && (W_rd != 0) && (W_rd == E_rs1))
            ForwardA = 2'b01;

        // EX Hazard (Forward from MA stage)
        if (M_regwrite && (M_rd != 0) && (M_rd == E_rs2))
            ForwardB = 2'b10;
        // MEM Hazard (Forward from WB stage)
        else if (W_regwrite && (W_rd != 0) && (W_rd == E_rs2))
            ForwardB = 2'b01;
    end
endmodule


// =============================================================================
// Module: Register File
// =============================================================================
module register_file(
    input clk,
    input rst_n,
    input [4:0] ra1, ra2, wa,
    input [31:0] wd,
    input we,
    output [31:0] rd1, rd2
);
    reg [31:0] registers [0:31];

    // Asynchronous Read
    assign rd1 = (ra1 == 0) ? 32'b0 : registers[ra1];
    assign rd2 = (ra2 == 0) ? 32'b0 : registers[ra2];

    // Write on Negative Edge (Half-cycle write) [cite: 170]
    // No initial block 
    always @(negedge clk) begin
        if (we && wa != 0) begin
            registers[wa] <= wd;
        end
    end
endmodule


// =============================================================================
// Module: Instruction Memory
// =============================================================================
module instruction_memory(
    input [31:0] addr,
    output [31:0] instr
);
    parameter MEM_DEPTH = 1024;
    reg [31:0] RAM [0:MEM_DEPTH-1];

    // Word Aligned Read
    assign instr = RAM[addr[31:2]]; 

endmodule


// =============================================================================
// Module: Data Memory
// =============================================================================
module data_memory(
    input clk,
    input [31:0] addr,
    input [31:0] write_data,
    input mem_write,
    output [31:0] read_data
);
    parameter MEM_DEPTH = 1024;
    reg [31:0] RAM [0:MEM_DEPTH-1];

    assign read_data = RAM[addr[31:2]];

    always @(posedge clk) begin
        if (mem_write)
            RAM[addr[31:2]] <= write_data;
    end
endmodule


// =============================================================================
// Module: Immediate Generator
// =============================================================================
module imm_gen(
    input [31:0] instr,
    output reg [31:0] imm_out
);
    wire [6:0] opcode = instr[6:0];
    
    always @(*) begin
        case (opcode)
            7'b0010011: imm_out = {{20{instr[31]}}, instr[31:20]}; // I-type (ADDI, etc)
            7'b0000011: imm_out = {{20{instr[31]}}, instr[31:20]}; // I-type (LW)
            7'b0100011: imm_out = {{20{instr[31]}}, instr[31:25], instr[11:7]}; // S-type (SW)
            7'b1100011: imm_out = {{20{instr[31]}}, instr[7], instr[30:25], instr[11:8], 1'b0}; // B-type (BEQ)
            7'b1101111: imm_out = {{12{instr[31]}}, instr[19:12], instr[20], instr[30:21], 1'b0}; // J-type (JAL)
            7'b0110111: imm_out = {instr[31:12], 12'b0}; // U-type (LUI)
            default:    imm_out = 32'b0;
        endcase
    end
endmodule


// =============================================================================
// Module: ALU
// =============================================================================
module alu(
    input [31:0] src_a, src_b,
    input [3:0] alu_control,
    output reg [31:0] alu_result,
    output zero
);
    wire signed [31:0] signed_a = src_a;
    wire signed [31:0] signed_b = src_b;
    wire [4:0] shamt = src_b[4:0];

    always @(*) begin
        case (alu_control)
            4'b0000: alu_result = src_a & src_b; // AND
            4'b0001: alu_result = src_a | src_b; // OR
            4'b0010: alu_result = src_a + src_b; // ADD
            4'b0011: alu_result = src_a - src_b; // SUB
            4'b0100: alu_result = (signed_a < signed_b) ? 32'b1 : 32'b0; // SLT
            4'b0101: alu_result = (src_a < src_b) ? 32'b1 : 32'b0;       // SLTU
            4'b0110: alu_result = src_a ^ src_b; // XOR
            4'b0111: alu_result = src_a << shamt; // SLL
            4'b1000: alu_result = src_a >> shamt; // SRL
            4'b1001: alu_result = signed_a >>> shamt; // SRA
            4'b1011: alu_result = src_b; // PASS_B (for LUI)
            default: alu_result = 32'b0;
        endcase
    end
    assign zero = (alu_result == 0);
endmodule


// =============================================================================
// Module: Control Unit
// =============================================================================
module control_unit(
    input [6:0] opcode,
    input [2:0] funct3,
    input [6:0] funct7,
    output reg regwrite, memwrite, memread, branch, alusrc, memtoreg, jump, lui,
    output reg [3:0] alucontrol
);
    reg [2:0] aluop; // Expanded to 3 bits

    always @(*) begin
        // Defaults
        regwrite = 0; memwrite = 0; memread = 0; branch = 0; 
        alusrc = 0; memtoreg = 0; jump = 0; lui = 0;
        aluop = 3'b000;

        case (opcode)
            7'b0110011: begin // R-type (ADD, SUB, AND, OR, XOR, SLL, SRL, SRA, SLT, SLTU)
                regwrite = 1; aluop = 3'b010;
            end
            7'b0010011: begin // I-type (ADDI, ANDI, ORI, XORI, SLTI, SLTIU, SLLI, SRLI, SRAI)
                regwrite = 1; alusrc = 1; aluop = 3'b010; // Use R-type encoding logic
            end
            7'b0000011: begin // LW
                regwrite = 1; alusrc = 1; memread = 1; memtoreg = 1; aluop = 3'b000;
            end
            7'b0100011: begin // SW
                memwrite = 1; alusrc = 1; aluop = 3'b000;
            end
            7'b1100011: begin // BEQ
                branch = 1; aluop = 3'b001;
            end
            7'b0110111: begin // LUI
                regwrite = 1; alusrc = 1; lui = 1; aluop = 3'b011; 
            end
            7'b1101111: begin // JAL
                regwrite = 1; jump = 1; aluop = 3'b100; // ALU not critical for PC calc here, handled by immediate
            end
        endcase
    end

    // ALU Control Decode
    always @(*) begin
        case (aluop)
            3'b000: alucontrol = 4'b0010; // ADD (LW/SW)
            3'b001: alucontrol = 4'b0011; // SUB (BEQ comparison)
            3'b011: alucontrol = 4'b1011; // LUI (Pass B)
            3'b100: alucontrol = 4'b0010; // JAL (Don't care, but can keep ADD)
            3'b010: begin // R-Type and I-Type Arithmetic
                case (funct3)
                    3'b000: begin // ADD/SUB/ADDI
                        if (opcode == 7'b0110011 && funct7 == 7'b0100000) 
                             alucontrol = 4'b0011; // SUB
                        else alucontrol = 4'b0010; // ADD, ADDI
                    end
                    3'b001: alucontrol = 4'b0111; // SLL, SLLI
                    3'b010: alucontrol = 4'b0100; // SLT, SLTI
                    3'b011: alucontrol = 4'b0101; // SLTU, SLTIU
                    3'b100: alucontrol = 4'b0110; // XOR, XORI
                    3'b101: begin // SRL/SRA, SRLI/SRAI
                        if (funct7 == 7'b0100000) alucontrol = 4'b1001; // SRA, SRAI
                        else                      alucontrol = 4'b1000; // SRL, SRLI
                    end
                    3'b110: alucontrol = 4'b0001; // OR, ORI
                    3'b111: alucontrol = 4'b0000; // AND, ANDI
                    default: alucontrol = 4'b0000;
                endcase
            end
            default: alucontrol = 4'b0000;
        endcase
    end
endmodule

tb_rv_pl.v
`include "rv_pl.v"
`timescale 1ns / 1ps

module tb_rv_pl;

    // =========================================================================
    // 1. Signals & Configuration
    // =========================================================================
    reg clk;
    reg rst_n;
    
    integer i;
    parameter MAX_CYCLES = 150; // Increased to accommodate the longer test program

    // =========================================================================
    // 2. DUT Instantiation
    // =========================================================================
    rv_pl dut (
        .clk(clk),
        .rst_n(rst_n)
    );

    // =========================================================================
    // 3. Clock Generation (100MHz -> 10ns period)
    // =========================================================================
    always #5 clk = ~clk;

    // =========================================================================
    // 4. Main Test Procedure
    // =========================================================================
    initial begin
        // Setup Waveform dumping
        $dumpfile("rv_pl_waveform.vcd");
        $dumpvars(0, tb_rv_pl);
        
        // Initialize signals
        clk = 0;
        rst_n = 0;

        // --- Memory Initialization ---
        // Ensure you compile the assembly to 'program.hex' before running
        $display("Loading program.hex...");
        // Note: Make sure the file exists or this will warning
        $readmemh("program.hex", dut.IMEM.RAM);

        // Initialize Data Memory and Registers for clean logs
        for (i = 0; i < 1024; i = i + 1) dut.DMEM.RAM[i] = 32'h0;
        for (i = 0; i < 32; i = i + 1) dut.RF.registers[i] = 32'h0;

        // --- Reset Sequence ---
        $display("Resetting Processor...");
        #20;
        rst_n = 1;
        $display("Processor Running...");

        // --- Run Simulation ---
        # (MAX_CYCLES * 10); 

        // --- End Simulation ---
        $display("\n--- Simulation Time Limit Reached ---");
        print_registers();
        $finish;
    end

    // =========================================================================
    // 5. Monitoring & Debugging (FIXED)
    // =========================================================================
    
    always @(posedge clk) begin
        if (rst_n) begin
            // 1. Check Write Back (WB) Stage for Register Writes
            // These instructions have effectively retired.
            if (dut.W_regwrite && dut.W_rd != 0) begin
                 $display("[%0t ns] WB: Reg x%0d <= 0x%h", $time, dut.W_rd, dut.W_result);
            end 
            
            // 2. Check Memory Access (MA) Stage for Store Completions
            // Stores retire at MA, so we check M_memwrite here.
            else if (dut.M_memwrite) begin
                 $display("[%0t ns] MA: Memory Store [Addr: 0x%h] <= Data: 0x%h", 
                          $time, dut.M_alu_res, dut.M_rs2_data);
            end 
            
            // 3. Check Jumps (Retired at WB for PC update context, though typically handled earlier)
            else if (dut.W_jump) begin
                 $display("[%0t ns] WB: Jump Link Addr Saved", $time);
            end

            // 4. Hazard Debugging
            if (dut.HAZARD.D_stall) 
                $display("\t\t>> STALL (Load-Use) <<");
            
            if (dut.HAZARD.E_flush) 
                $display("\t\t>> FLUSH (Control/Branch) <<");
        end
    end

    // Task to print register file contents
    task print_registers;
        begin
            $display("\n==========================================");
            $display(" Final Register File State");
            $display("==========================================");
            for (i = 0; i < 32; i = i + 1) begin
                if (i % 4 == 0) $write("\n x%02d: ", i);
                $write("%h ", dut.RF.registers[i]);
            end
            $display("\n==========================================\n");
            $display("Final Memory[0]: %h", dut.DMEM.RAM[0]);
        end
    endtask

endmodule

rv_pl_waveform.vcd
$date
	Sun Jan 11 05:43:36 2026
$end
$version
	Icarus Verilog
$end
$timescale
	1ps
$end
$scope module tb_rv_pl $end
$var parameter 32 ! MAX_CYCLES $end
$var reg 1 " clk $end
$var reg 1 # rst_n $end
$var integer 32 $ i [31:0] $end
$scope module dut $end
$var wire 1 % E_branch_taken $end
$var wire 32 & E_op1 [31:0] $end
$var wire 1 " clk $end
$var wire 1 # rst_n $end
$var wire 32 ' W_result [31:0] $end
$var wire 1 ( PC_en $end
$var wire 32 ) M_mem_data [31:0] $end
$var wire 2 * ForwardB [1:0] $end
$var wire 2 + ForwardA [1:0] $end
$var wire 32 , F_instr [31:0] $end
$var wire 32 - F_PC_plus_4 [31:0] $end
$var wire 32 . F_PC_next [31:0] $end
$var wire 32 / F_PC [31:0] $end
$var wire 1 0 E_zero $end
$var wire 32 1 E_target_PC [31:0] $end
$var wire 32 2 E_op2 [31:0] $end
$var wire 32 3 E_forwarded_rs2 [31:0] $end
$var wire 32 4 E_forwarded_rs1 [31:0] $end
$var wire 1 5 E_flush $end
$var wire 32 6 E_alu_res [31:0] $end
$var wire 1 7 D_stall $end
$var wire 32 8 D_rs2_data [31:0] $end
$var wire 5 9 D_rs2 [4:0] $end
$var wire 32 : D_rs1_data [31:0] $end
$var wire 5 ; D_rs1 [4:0] $end
$var wire 1 < D_regwrite $end
$var wire 5 = D_rd [4:0] $end
$var wire 7 > D_opcode [6:0] $end
$var wire 1 ? D_memwrite $end
$var wire 1 @ D_memtoreg $end
$var wire 1 A D_memread $end
$var wire 1 B D_lui $end
$var wire 1 C D_jump $end
$var wire 32 D D_imm [31:0] $end
$var wire 7 E D_funct7 [6:0] $end
$var wire 3 F D_funct3 [2:0] $end
$var wire 1 G D_flush $end
$var wire 1 H D_branch $end
$var wire 1 I D_alusrc $end
$var wire 4 J D_alucontrol [3:0] $end
$var reg 32 K D_PC [31:0] $end
$var reg 32 L D_PC_plus_4 [31:0] $end
$var reg 32 M D_instr [31:0] $end
$var reg 32 N E_PC [31:0] $end
$var reg 32 O E_PC_plus_4 [31:0] $end
$var reg 4 P E_alucontrol [3:0] $end
$var reg 1 Q E_alusrc $end
$var reg 1 R E_branch $end
$var reg 32 S E_imm [31:0] $end
$var reg 1 T E_jump $end
$var reg 1 U E_lui $end
$var reg 1 V E_memread $end
$var reg 1 W E_memtoreg $end
$var reg 1 X E_memwrite $end
$var reg 5 Y E_rd [4:0] $end
$var reg 1 Z E_regwrite $end
$var reg 5 [ E_rs1 [4:0] $end
$var reg 32 \ E_rs1_data [31:0] $end
$var reg 5 ] E_rs2 [4:0] $end
$var reg 32 ^ E_rs2_data [31:0] $end
$var reg 32 _ M_PC_plus_4 [31:0] $end
$var reg 32 ` M_alu_res [31:0] $end
$var reg 1 a M_jump $end
$var reg 1 b M_memread $end
$var reg 1 c M_memtoreg $end
$var reg 1 d M_memwrite $end
$var reg 5 e M_rd [4:0] $end
$var reg 1 f M_regwrite $end
$var reg 32 g M_rs2_data [31:0] $end
$var reg 32 h PC [31:0] $end
$var reg 32 i W_PC_plus_4 [31:0] $end
$var reg 32 j W_alu_res [31:0] $end
$var reg 1 k W_jump $end
$var reg 32 l W_mem_data [31:0] $end
$var reg 1 m W_memtoreg $end
$var reg 5 n W_rd [4:0] $end
$var reg 1 o W_regwrite $end
$scope module ALU_UNIT $end
$var wire 4 p alu_control [3:0] $end
$var wire 32 q signed_a [31:0] $end
$var wire 32 r signed_b [31:0] $end
$var wire 32 s src_a [31:0] $end
$var wire 32 t src_b [31:0] $end
$var wire 1 0 zero $end
$var wire 5 u shamt [4:0] $end
$var reg 32 v alu_result [31:0] $end
$upscope $end
$scope module CTRL $end
$var wire 3 w funct3 [2:0] $end
$var wire 7 x funct7 [6:0] $end
$var wire 7 y opcode [6:0] $end
$var reg 4 z alucontrol [3:0] $end
$var reg 3 { aluop [2:0] $end
$var reg 1 I alusrc $end
$var reg 1 H branch $end
$var reg 1 C jump $end
$var reg 1 B lui $end
$var reg 1 A memread $end
$var reg 1 @ memtoreg $end
$var reg 1 ? memwrite $end
$var reg 1 < regwrite $end
$upscope $end
$scope module DMEM $end
$var wire 32 | addr [31:0] $end
$var wire 1 " clk $end
$var wire 1 d mem_write $end
$var wire 32 } read_data [31:0] $end
$var wire 32 ~ write_data [31:0] $end
$var parameter 32 !" MEM_DEPTH $end
$upscope $end
$scope module EXT $end
$var wire 32 "" instr [31:0] $end
$var wire 7 #" opcode [6:0] $end
$var reg 32 $" imm_out [31:0] $end
$upscope $end
$scope module FWD $end
$var wire 5 %" E_rs1 [4:0] $end
$var wire 5 &" E_rs2 [4:0] $end
$var wire 5 '" M_rd [4:0] $end
$var wire 1 f M_regwrite $end
$var wire 5 (" W_rd [4:0] $end
$var wire 1 o W_regwrite $end
$var reg 2 )" ForwardA [1:0] $end
$var reg 2 *" ForwardB [1:0] $end
$upscope $end
$scope module HAZARD $end
$var wire 5 +" D_rs1 [4:0] $end
$var wire 5 ," D_rs2 [4:0] $end
$var wire 1 % E_branch_taken $end
$var wire 1 V E_memread $end
$var wire 5 -" E_rd [4:0] $end
$var reg 1 G D_flush $end
$var reg 1 7 D_stall $end
$var reg 1 5 E_flush $end
$var reg 1 ( PC_en $end
$upscope $end
$scope module IMEM $end
$var wire 32 ." addr [31:0] $end
$var wire 32 /" instr [31:0] $end
$var parameter 32 0" MEM_DEPTH $end
$upscope $end
$scope module RF $end
$var wire 1 " clk $end
$var wire 5 1" ra1 [4:0] $end
$var wire 5 2" ra2 [4:0] $end
$var wire 1 # rst_n $end
$var wire 5 3" wa [4:0] $end
$var wire 32 4" wd [31:0] $end
$var wire 1 o we $end
$var wire 32 5" rd2 [31:0] $end
$var wire 32 6" rd1 [31:0] $end
$upscope $end
$upscope $end
$scope task print_registers $end
$upscope $end
$upscope $end
$enddefinitions $end
$comment Show the parameter values. $end
$dumpall
b10000000000 0"
b10000000000 !"
b10010110 !
$end
#0
$dumpvars
bx 6"
bx 5"
bx 4"
bx 3"
bx 2"
bx 1"
bx /"
bx ."
bx -"
bx ,"
bx +"
bx *"
bx )"
bx ("
bx '"
bx &"
bx %"
bx $"
bx #"
bx ""
bx ~
bx }
bx |
bx {
bx z
bx y
bx x
bx w
bx v
bx u
bx t
bx s
bx r
bx q
bx p
xo
bx n
xm
bx l
xk
bx j
bx i
bx h
bx g
xf
bx e
xd
xc
xb
xa
bx `
bx _
bx ^
bx ]
bx \
bx [
xZ
bx Y
xX
xW
xV
xU
xT
bx S
xR
xQ
bx P
bx O
bx N
bx M
bx L
bx K
bx J
xI
xH
xG
bx F
bx E
bx D
xC
xB
xA
x@
x?
bx >
bx =
x<
bx ;
bx :
bx 9
bx 8
x7
bx 6
x5
bx 4
bx 3
bx 2
bx 1
x0
bx /
bx .
bx -
bx ,
bx +
bx *
bx )
x(
bx '
bx &
x%
b100000 $
0#
0"
$end
#5000
b0 u
b0 r
b0 2
b0 t
10
b0 6
b0 v
b0 {
0B
0C
0@
0I
0H
0A
0?
0<
b0 :
b0 6"
b0 8
b0 5"
b10 J
b10 z
b0 3
b0 q
b0 &
b0 s
b0 4
b101000000000000010010011 ,
b101000000000000010010011 /"
b0 >
b0 y
b0 =
b0 F
b0 w
b0 ;
b0 +"
b0 1"
b0 9
b0 ,"
b0 2"
b0 E
b0 x
b0 D
b0 $"
b0 #"
0%
05
0G
07
1(
b100 .
b0 )
b0 }
b0 '
b0 4"
b0 *
b0 *"
b0 +
b0 )"
b100 -
b0 /
b0 h
b0 ."
b0 L
b0 M
b0 ""
b0 K
0U
0T
0W
0Q
0R
0V
0X
0Z
b0 P
b0 p
b0 Y
b0 -"
b0 ]
b0 &"
b0 [
b0 %"
b0 O
b0 1
b0 S
b0 ^
b0 \
b0 N
0a
0c
0b
0d
0f
b0 _
b0 e
b0 '"
b0 g
b0 ~
b0 `
b0 |
0k
0m
0o
b0 i
b0 n
b0 ("
b0 3"
b0 j
b0 l
1"
#10000
0"
#15000
1"
#20000
0"
1#
#25000
b10 {
1I
1<
b1000 .
b10100000000000100010011 ,
b10100000000000100010011 /"
b10011 >
b10011 y
b1 =
b1010 9
b1010 ,"
b1010 2"
b1010 D
b1010 $"
b10011 #"
b1000 -
b100 /
b100 h
b100 ."
b100 L
b101000000000000010010011 M
b101000000000000010010011 ""
b10 P
b10 p
1"
#30000
0"
#35000
00
b1010 6
b1010 v
b1010 u
b1010 r
b1010 2
b1010 t
b10 =
b101 9
b101 ,"
b101 2"
b101 D
b101 $"
b1100 .
b11111111111100000000000110010011 ,
b11111111111100000000000110010011 /"
1Q
1Z
b1 Y
b1 -"
b1010 ]
b1010 &"
b100 O
b1010 1
b1010 S
b1000 L
b10100000000000100010011 M
b10100000000000100010011 ""
b100 K
b1100 -
b1000 /
b1000 h
b1000 ."
1"
#40000
0"
#45000
b101 6
b101 v
b101 u
b10000 .
b1000001000001000110011 ,
b1000001000001000110011 /"
b11 =
b11111 9
b11111 ,"
b11111 2"
b1111111 E
b1111111 x
b11111111111111111111111111111111 D
b11111111111111111111111111111111 $"
b101 r
b101 2
b101 t
b10000 -
b1100 /
b1100 h
b1100 ."
b1100 L
b11111111111100000000000110010011 M
b11111111111100000000000110010011 ""
b1000 K
b10 Y
b10 -"
b101 ]
b101 &"
b1000 O
b101 S
b1001 1
b100 N
1f
b100 _
b1 e
b1 '"
b1010 `
b1010 |
1"
#50000
0"
#55000
b1010 '
b1010 4"
b11111111111111111111111111111111 6
b11111111111111111111111111111111 v
b11111 u
b10 {
0I
1<
b11111111111111111111111111111111 r
b11111111111111111111111111111111 2
b11111111111111111111111111111111 t
b110011 >
b110011 y
b100 =
b1 ;
b1 +"
b1 1"
b10 9
b10 ,"
b10 2"
b0 E
b0 x
b0 D
b0 $"
b110011 #"
b10100 .
b1000000001000001000001010110011 ,
b1000000001000001000001010110011 /"
1o
b100 i
b1 n
b1 ("
b1 3"
b1010 j
b1000 _
b10 e
b10 '"
b101 `
b101 |
b11 Y
b11 -"
b11111 ]
b11111 &"
b1100 O
b11111111111111111111111111111111 S
b111 1
b1000 N
b10000 L
b1000001000001000110011 M
b1000001000001000110011 ""
b1100 K
b10100 -
b10000 /
b10000 h
b10000 ."
1"
#60000
b1010 :
b1010 6"
0"
