custom_ip/rv-sc-ip.v
//==============================================================================
// mux2 - 2:1 multiplexer
//==============================================================================
module mux2 #(parameter WIDTH = 32) (
    input  wire [WIDTH-1:0] a,
    input  wire [WIDTH-1:0] b,
    input  wire             sel,
    output wire [WIDTH-1:0] y
);
    assign y = sel ? b : a;
endmodule

//==============================================================================
// adder - 32-bit adder
//==============================================================================
module adder (
    input  wire [31:0] a,
    input  wire [31:0] b,
    output wire [31:0] y
);
    assign y = a + b;
endmodule

//==============================================================================
// alu - Arithmetic/Logic Unit
//==============================================================================
module alu (
    input  wire [31:0] a,
    input  wire [31:0] b,
    input  wire [3:0]  alu_control,
    output reg  [31:0] y,
    output wire        zero
);
    assign zero = (y == 32'b0);

    always @(*) begin
        case (alu_control)
            4'b0000: y = a + b;                   // add
            4'b0001: y = a - b;                   // sub
            4'b0010: y = a << b[4:0];             // sll
            4'b0011: y = ($signed(a) < $signed(b)) ? 32'b1 : 32'b0; // slt
            4'b0100: y = (a < b) ? 32'b1 : 32'b0; // sltu
            4'b0101: y = a ^ b;                   // xor
            4'b0110: y = a >> b[4:0];             // srl (logical)
            4'b0111: y = $signed(a) >>> b[4:0];   // sra (arithmetic)
            4'b1000: y = a | b;                   // or
            4'b1001: y = a & b;                   // and
            default: y = 32'b0;
        endcase
    end

endmodule

//==============================================================================
// sign_ext - Sign/zero extension for immediates
//==============================================================================
module sign_ext (
    input  wire [31:0] instr,
    input  wire [2:0]  imm_sel,
    output reg  [31:0] imm
);

    always @(*) begin
        case (imm_sel)

            // I-type
            3'b000: imm = {{20{instr[31]}}, instr[31:20]};

            // S-type
            3'b001: imm = {{20{instr[31]}}, instr[31:25], instr[11:7]};

            // B-type (branch)
            3'b010: imm = {{19{instr[31]}},
                           instr[31],
                           instr[7],
                           instr[30:25],
                           instr[11:8],
                           1'b0};

            // U-type (lui)
            3'b011: imm = {instr[31:12], 12'b0};

            // J-type (jal)
            3'b100: imm = {{11{instr[31]}},
                           instr[31],
                           instr[19:12],
                           instr[20],
                           instr[30:21],
                           1'b0};

            default: imm = 32'b0;

        endcase
    end

endmodule

//==============================================================================
// pc - Program counter
//==============================================================================
module pc (
    input  wire        clk,
    input  wire        reset,
    input  wire [31:0] next_pc,
    output reg  [31:0] pc
);

    always @(posedge clk) begin
        if (reset)
            pc <= 32'b0;
        else
            pc <= next_pc;
    end

endmodule

//==============================================================================
// regfile - Register file
//==============================================================================
module regfile (
    input  wire        clk,
    input  wire        we,
    input  wire [4:0]  rs1, rs2, rd,
    input  wire [31:0] wd,
    output wire [31:0] rd1, rd2
);
    reg [31:0] regs [31:0];

    // write
    always @(posedge clk) begin
        if (we && rd != 0)
            regs[rd] <= wd;
    end

    // read
    assign rd1 = (rs1 == 0) ? 0 : regs[rs1];
    assign rd2 = (rs2 == 0) ? 0 : regs[rs2];

endmodule

//==============================================================================
// controller - Main control and ALU control
//==============================================================================
module controller (
    input  wire [6:0] opcode,
    input  wire [2:0] funct3,
    input  wire [6:0] funct7,

    output reg        rf_we,
    output reg [2:0]  imm_sel,
    output reg        sel_alu_src_b,
    output reg        dmem_we,
    output reg [1:0]  sel_result,
    output reg [1:0]  alu_op,
    output reg [3:0]  alu_control,
    output reg        branch,
    output reg        jump
);

    always @(*) begin
        rf_we         = 0;
        imm_sel       = 3'b000;
        sel_alu_src_b = 0;
        dmem_we       = 0;
        sel_result    = 2'b00;
        alu_op        = 2'b00;
        branch        = 0;
        jump          = 0;

        case (opcode)
            7'b0110011: begin
                rf_we         = 1;
                sel_alu_src_b = 0;
                sel_result    = 2'b00;
                alu_op        = 2'b01;
            end
            7'b0010011: begin
                rf_we         = 1;
                imm_sel       = 3'b000;
                sel_alu_src_b = 1;
                sel_result    = 2'b00;
                alu_op        = 2'b10;
            end
            7'b0000011: begin
                rf_we         = 1;
                imm_sel       = 3'b000;
                sel_alu_src_b = 1;
                sel_result    = 2'b01;
                alu_op        = 2'b00;
            end
            7'b0100011: begin
                imm_sel       = 3'b001;
                sel_alu_src_b = 1;
                dmem_we       = 1;
                alu_op        = 2'b00;
            end
            7'b1100011: begin
                branch        = 1;
                imm_sel       = 3'b010;
                sel_alu_src_b = 0;
                alu_op        = 2'b11;
            end
            7'b1101111: begin
                jump          = 1;
                rf_we         = 1;
                imm_sel       = 3'b100;
                sel_result    = 2'b10;
            end
            7'b0110111: begin
                rf_we         = 1;
                imm_sel       = 3'b011;
                sel_result    = 2'b11;
            end
        endcase
    end

    always @(*) begin
        alu_control = 4'b0000;

        case (alu_op)

            2'b00: alu_control = 4'b0000;

            2'b01: begin
                case (funct3)
                    3'b000: alu_control = (funct7 == 7'b0100000) ? 4'b0001 : 4'b0000;
                    3'b001: alu_control = 4'b0010;
                    3'b010: alu_control = 4'b0011;
                    3'b011: alu_control = 4'b0100;
                    3'b100: alu_control = 4'b0101;
                    3'b101: alu_control = (funct7 == 7'b0100000) ? 4'b0111 : 4'b0110;
                    3'b110: alu_control = 4'b1000;
                    3'b111: alu_control = 4'b1001;
                endcase
            end

            2'b10: begin
                case (funct3)
                    3'b000: alu_control = 4'b0000;
                    3'b010: alu_control = 4'b0011;
                    3'b011: alu_control = 4'b0100;
                    3'b100: alu_control = 4'b0101;
                    3'b110: alu_control = 4'b1000;
                    3'b111: alu_control = 4'b1001;
                    3'b001: alu_control = 4'b0010;
                    3'b101: alu_control = (funct7 == 7'b0100000) ? 4'b0111 : 4'b0110;
                endcase
            end

            2'b11: begin
                case (funct3)
                    3'b000: alu_control = 4'b0001;
                    default: alu_control = 4'b0000;
                endcase
            end

        endcase
    end

endmodule

//==============================================================================
// rv_sc_ip - Top-level CPU adapted for BRAM testbench integration
//==============================================================================
module rv_sc_ip #(
    parameter ADDR_WIDTH = 12
)(
    input  wire        clk,
    input  wire        resetn,

    // Instruction BRAM Interface
    output wire        i_clkb,
    output wire        i_enb,
    output wire [3:0]  i_web,
    output wire [31:0] i_addrb,
    output wire [31:0] i_dinb,
    input  wire [31:0] i_doutb,

    // Data BRAM Interface
    output wire        d_clkb,
    output wire        d_enb,
    output wire [3:0]  d_web,
    output wire [31:0] d_addrb,
    output wire [31:0] d_dinb,
    input  wire [31:0] d_doutb
);

    // 1. Core Signals & Active-High Reset Conversion
    wire reset = ~resetn; 
    
    // 2. Internal Datapath Wires
    wire [31:0] pc, next_pc, pc_plus_4, pc_target;
    
    // Incoming BRAM data
    wire [31:0] instr   = i_doutb;
    wire [31:0] dmem_rd = d_doutb;
    
    wire [6:0] opcode = instr[6:0];
    wire [4:0] rd     = instr[11:7];
    wire [2:0] funct3 = instr[14:12];
    wire [4:0] rs1    = instr[19:15];
    wire [4:0] rs2    = instr[24:20];
    wire [6:0] funct7 = instr[31:25];

    wire        rf_we, sel_alu_src_b, dmem_we;
    wire [2:0]  imm_sel;
    wire [1:0]  sel_result;
    wire [1:0]  alu_op;
    wire [3:0]  alu_control;
    wire        branch, jump;

    wire [31:0] rd1, rd2;
    wire [31:0] imm;
    wire [31:0] alu_b_src;
    wire [31:0] alu_y;
    wire        alu_zero;
    wire [31:0] result;
    wire        take_branch;

    // 3. BRAM Interface Mapping
    // We invert the BRAM clock so synchronous reads happen mid-cycle. 
    // This perfectly emulates asynchronous memory behavior for a single-cycle core.
    assign i_clkb  = ~clk;
    assign i_enb   = 1'b1;
    assign i_web   = 4'b0000;
    assign i_addrb = pc;
    assign i_dinb  = 32'b0;

    assign d_clkb  = ~clk;
    assign d_enb   = 1'b1;
    // Write-enable needs to be broadcast to all 4 byte-enables if dmem_we is high
    assign d_web   = dmem_we ? 4'b1111 : 4'b0000;
    assign d_addrb = alu_y;
    assign d_dinb  = rd2;

    

    

    // 4. Sub-Module Instantiations
    pc u_pc (
        .clk(clk),
        .reset(reset),
        .next_pc(next_pc),
        .pc(pc)
    );

    adder u_pc_adder (
        .a(pc),
        .b(32'd4),
        .y(pc_plus_4)
    );

    controller u_controller (
        .opcode(opcode),
        .funct3(funct3),
        .funct7(funct7),
        .rf_we(rf_we),
        .imm_sel(imm_sel),
        .sel_alu_src_b(sel_alu_src_b),
        .dmem_we(dmem_we),
        .sel_result(sel_result),
        .alu_control(alu_control),
        .branch(branch),
        .jump(jump)
    );

    regfile u_regfile (
        .clk(clk),
        .we(rf_we),
        .rs1(rs1),
        .rs2(rs2),
        .rd(rd),
        .wd(result),
        .rd1(rd1),
        .rd2(rd2)
    );

    sign_ext u_sign_ext (
        .instr(instr),
        .imm_sel(imm_sel),
        .imm(imm)
    );

    mux2 #(32) u_alu_src_mux (
        .a(rd2),
        .b(imm),
        .sel(sel_alu_src_b),
        .y(alu_b_src)
    );

    alu u_alu (
        .a(rd1),
        .b(alu_b_src),
        .alu_control(alu_control),
        .y(alu_y),
        .zero(alu_zero)
    );

    // Write-back Muxes
    wire [31:0] sel_res0 = (sel_result == 2'b00) ? alu_y   :
                           (sel_result == 2'b01) ? dmem_rd : 32'b0;

    wire [31:0] sel_res1 = (sel_result == 2'b10) ? pc_plus_4 :
                           (sel_result == 2'b11) ? imm       : 32'b0;

    assign result = (sel_result[1] == 1'b0) ? sel_res0 : sel_res1;

    // Branch Logic
    adder u_branch_adder (
        .a(pc),
        .b(imm),
        .y(pc_target)
    );

    assign take_branch = branch && alu_zero;

    // Next PC Selection
    assign next_pc = jump        ? pc_target :
                     take_branch ? pc_target :
                                   pc_plus_4;

endmodule

tb-rv-sc.v
`timescale 1ns/1ps

module tb_rv_sc();

    // 1. Clock and Reset Generation
    reg clk;
    reg resetn;

    always #5 clk = ~clk; // 100 MHz clock

    // 2. DUT Signals & Instantiation
    // I-BRAM ports
    wire        i_clkb;
    wire        i_enb;
    wire [3:0]  i_web;
    wire [31:0] i_addrb;
    wire [31:0] i_dinb;
    reg  [31:0] i_doutb;

    // D-BRAM ports
    wire        d_clkb;
    wire        d_enb;
    wire [3:0]  d_web;
    wire [31:0] d_addrb;
    wire [31:0] d_dinb;
    reg  [31:0] d_doutb;

    rv_sc_ip #(.ADDR_WIDTH(12)) DUT (
        .clk(clk),
        .resetn(resetn),

        .i_clkb(i_clkb),
        .i_enb(i_enb),
        .i_web(i_web),
        .i_addrb(i_addrb),
        .i_dinb(i_dinb),
        .i_doutb(i_doutb),

        .d_clkb(d_clkb),
        .d_enb(d_enb),
        .d_web(d_web),
        .d_addrb(d_addrb),
        .d_dinb(d_dinb),
        .d_doutb(d_doutb)
    );


    // 3. Simulated Synchronous BRAMs
    reg [31:0] i_bram [0:4095]; // 16KB Instruction Memory
    reg [31:0] d_bram [0:4095]; // 16KB Data Memory

    always @(posedge i_clkb) begin
        if (i_enb) begin
            i_doutb <= i_bram[i_addrb[13:2]];
        end
    end

    always @(posedge d_clkb) begin
        if (d_enb) begin
            if (d_web == 4'b1111) begin
                d_bram[d_addrb[13:2]] <= d_dinb;
            end
            d_doutb <= d_bram[d_addrb[13:2]];
        end
    end

    // 4. Jupyter Notebook PS Simulation
    
    // Test Parameters
    localparam NUM_ELEMENTS = 32;
    localparam DATA_BASE_ADDR = 32'h00000040;
    localparam STATUS_ADDR = 32'h0000200; // Status Flag Address
    localparam MAGIC_NUM_1 = 32'hCAFEBABE;
    localparam MAGIC_NUM_2 = 32'hDEADBEAF;

    reg signed [31:0] golden_array [0:NUM_ELEMENTS-1];
    reg signed [31:0] temp;
    integer i, j, errors;

    initial begin
        // Initialize signals
        clk = 0;
        resetn = 0;
        errors = 0;

        $display("--------------------------------------------------");
        $display("[PS HOST] Phase 1: Initialization & Injection");
        
        $readmemh("test-program.hex", i_bram);
        $display("[PS HOST] Loaded sort.hex into I-BRAM.");

        $display("[PS HOST] Generating 32 random signed integers...");
        for (i = 0; i < NUM_ELEMENTS; i = i + 1) begin
            golden_array[i] = $random;
            d_bram[(DATA_BASE_ADDR >> 2) + i] = golden_array[i];
        end

        for (i = NUM_ELEMENTS - 1; i > 0; i = i - 1) begin
            for (j = 0; j < i; j = j + 1) begin
                if (golden_array[j] > golden_array[j+1]) begin
                    temp = golden_array[j];
                    golden_array[j] = golden_array[j+1];
                    golden_array[j+1] = temp;
                end
            end
        end
        
        d_bram[STATUS_ADDR >> 2] = 32'h00000000;

        $display("--------------------------------------------------");
        $display("[PS HOST] Phase 2: Execution");
        
        #100;
        resetn = 1; 
        $display("[PS HOST] Released Reset. RISC-V Core is now running...");

        // 5. Polling & Verification
        $display("[PS HOST] Phase 3: Verification (Polling Status Flag...)");
        
        // Polling loop
        while (d_bram[STATUS_ADDR >> 2] !== MAGIC_NUM_1 && d_bram[STATUS_ADDR >> 2] !== MAGIC_NUM_2) begin
    @(posedge clk); // Wait for the next clock edge before checking again
end
        
        $display("--------------------------------------------------");
        $display("[PS HOST] Magic Number Detected! Core execution finished.");
        $display("[PS HOST] Retrieving results and performing Automated Checking...");

        // Retrieve Results and Compare
        for (i = 0; i < NUM_ELEMENTS; i = i + 1) begin
            $display("DRAM: %0d, Golden: %0d", $signed(d_bram[(DATA_BASE_ADDR >> 2) + i]), golden_array[i]);
            if ($signed(d_bram[(DATA_BASE_ADDR >> 2) + i]) !== golden_array[i]) begin
                $display("FAILURE: Mismatch at index %0d. Expected: %0d, Got: %0d", 
                         i, golden_array[i], $signed(d_bram[(DATA_BASE_ADDR >> 2) + i]));
                errors = errors + 1;
            end
        end

        if (errors == 0) begin
            $display("----------------------------------------");
            $display("                SUCCESS!                ");
            $display("----------------------------------------");
        end else begin
            $display("----------------------------------------");
            $display("        TEST FAILED WITH %0d ERRORS       ", errors);
            $display("----------------------------------------");
        end

        #100 $finish;
    end

    initial begin
        $dumpfile("rv_sc.vcd");
        $dumpvars(0, tb_rv_sc);
    end

endmodule

hdl_group_project.tmp/edit_ip_project.sim/sim_1/behav/xsim/rv_sc.vcd
$date
   Fri Feb 20 22:16:34 2026
$end
$version
  2021.2
$end
$timescale
  1ps
$end
$scope module tb_rv_sc $end
$var reg 1 ! clk $end
$var reg 1 " resetn $end
$var wire 1 # i_clkb $end
$var wire 1 $ i_enb $end
$var wire 4 % i_web [3:0] $end
$var wire 32 & i_addrb [31:0] $end
$var wire 32 ' i_dinb [31:0] $end
$var reg 32 ( i_doutb [31:0] $end
$var wire 1 ) d_clkb $end
$var wire 1 * d_enb $end
$var wire 4 + d_web [3:0] $end
$var wire 32 , d_addrb [31:0] $end
$var wire 32 - d_dinb [31:0] $end
$var reg 32 . d_doutb [31:0] $end
$var reg 32 / temp [31:0] $end
$var integer 32 0 i [31:0] $end
$var integer 32 1 j [31:0] $end
$var integer 32 2 errors [31:0] $end
$scope module DUT $end
$var wire 1 3 clk $end
$var wire 1 4 resetn $end
$var wire 1 # i_clkb $end
$var wire 1 $ i_enb $end
$var wire 4 % i_web [3:0] $end
$var wire 32 & i_addrb [31:0] $end
$var wire 32 ' i_dinb [31:0] $end
$var wire 32 5 i_doutb [31:0] $end
$var wire 1 ) d_clkb $end
$var wire 1 * d_enb $end
$var wire 4 + d_web [3:0] $end
$var wire 32 , d_addrb [31:0] $end
$var wire 32 - d_dinb [31:0] $end
$var wire 32 6 d_doutb [31:0] $end
$var wire 1 7 reset $end
$var wire 32 8 pc [31:0] $end
$var wire 32 9 next_pc [31:0] $end
$var wire 32 : pc_plus_4 [31:0] $end
$var wire 32 ; pc_target [31:0] $end
$var wire 32 < instr [31:0] $end
$var wire 32 = dmem_rd [31:0] $end
$var wire 7 > opcode [6:0] $end
$var wire 5 ? rd [4:0] $end
$var wire 3 @ funct3 [2:0] $end
$var wire 5 A rs1 [4:0] $end
$var wire 5 B rs2 [4:0] $end
$var wire 7 C funct7 [6:0] $end
$var wire 1 D rf_we $end
$var wire 1 E sel_alu_src_b $end
$var wire 1 F dmem_we $end
$var wire 3 G imm_sel [2:0] $end
$var wire 2 H sel_result [1:0] $end
$var wire 2 I alu_op [1:0] $end
$var wire 4 J alu_control [3:0] $end
$var wire 1 K branch $end
$var wire 1 L jump $end
$var wire 32 M rd1 [31:0] $end
$var wire 32 N rd2 [31:0] $end
$var wire 32 O imm [31:0] $end
$var wire 32 P alu_b_src [31:0] $end
$var wire 32 Q alu_y [31:0] $end
$var wire 1 R alu_zero $end
$var wire 32 S result [31:0] $end
$var wire 1 T take_branch $end
$var wire 32 U sel_res0 [31:0] $end
$var wire 32 V sel_res1 [31:0] $end
$scope module u_pc $end
$var wire 1 3 clk $end
$var wire 1 7 reset $end
$var wire 32 9 next_pc [31:0] $end
$var reg 32 W pc [31:0] $end
$upscope $end
$scope module u_pc_adder $end
$var wire 32 8 a [31:0] $end
$var wire 32 X b [31:0] $end
$var wire 32 : y [31:0] $end
$upscope $end
$scope module u_controller $end
$var wire 7 > opcode [6:0] $end
$var wire 3 @ funct3 [2:0] $end
$var wire 7 C funct7 [6:0] $end
$var reg 1 Y rf_we $end
$var reg 3 Z imm_sel [2:0] $end
$var reg 1 [ sel_alu_src_b $end
$var reg 1 \ dmem_we $end
$var reg 2 ] sel_result [1:0] $end
$var reg 2 ^ alu_op [1:0] $end
$var reg 4 _ alu_control [3:0] $end
$var reg 1 ` branch $end
$var reg 1 a jump $end
$upscope $end
$scope module u_regfile $end
$var wire 1 3 clk $end
$var wire 1 D we $end
$var wire 5 A rs1 [4:0] $end
$var wire 5 B rs2 [4:0] $end
$var wire 5 ? rd [4:0] $end
$var wire 32 S wd [31:0] $end
$var wire 32 M rd1 [31:0] $end
$var wire 32 N rd2 [31:0] $end
$upscope $end
$scope module u_sign_ext $end
$var wire 32 < instr [31:0] $end
$var wire 3 G imm_sel [2:0] $end
$var reg 32 b imm [31:0] $end
$upscope $end
$scope module u_alu_src_mux $end
$var wire 32 N a [31:0] $end
$var wire 32 O b [31:0] $end
$var wire 1 E sel $end
$var wire 32 P y [31:0] $end
$upscope $end
$scope module u_alu $end
$var wire 32 M a [31:0] $end
$var wire 32 P b [31:0] $end
$var wire 4 J alu_control [3:0] $end
$var reg 32 c y [31:0] $end
$var wire 1 R zero $end
$upscope $end
$scope module u_branch_adder $end
$var wire 32 8 a [31:0] $end
$var wire 32 O b [31:0] $end
$var wire 32 ; y [31:0] $end
$upscope $end
$upscope $end
$upscope $end
$enddefinitions $end
#0
$dumpvars
0!
0"
1#
1$
b0 %
bx &
b0 '
bx (
1)
1*
bx +
bx ,
bx -
bx .
b10110001111100000101011001100011 /
b0 0
b1 1
b0 2
03
04
bx 5
bx 6
17
bx 8
bx 9
bx :
bx ;
bx <
bx =
bx >
bx ?
bx @
bx A
bx B
bx C
xD
xE
xF
bx G
bx H
bz I
bx J
xK
xL
bx M
bx N
bx O
bx P
bx Q
xR
bx S
xT
bx U
bx V
bx W
b100 X
xY
bx Z
x[
x\
bx ]
bx ^
bx _
x`
xa
bx b
bx c
$end
#5000
1!
0#
b0 &
0)
13
b0 8
b100 :
bx ;
bx V
b0 W
#10000
0!
1#
b100000000000000000001010010011 (
1)
b0 +
b1000000000 ,
b0 -
03
b100000000000000000001010010011 5
b100 9
b1000000000 ;
b100000000000000000001010010011 <
b10011 >
b101 ?
b0 @
b0 A
b0 B
b10000 C
1D
1E
0F
b0 G
b0 H
b0 J
0K
0L
b0 M
b0 N
b1000000000 O
b1000000000 P
b1000000000 Q
0R
b1000000000 S
0T
b1000000000 U
b0 V
1Y
b0 Z
1[
0\
b0 ]
b10 ^
b0 _
0`
0a
b1000000000 b
b1000000000 c
#15000
1!
0#
0)
13
b0 M
b0 N
#20000
0!
1#
1)
b0 .
03
b0 6
b0 =
b1000000000 U
#25000
1!
0#
0)
13
#30000
0!
1#
1)
03
#35000
1!
0#
0)
13
#40000
0!
1#
1)
03
#45000
1!
0#
0)
13
#50000
0!
1#
1)
03
#55000
1!
0#
0)
13
#60000
0!
1#
1)
03
#65000
1!
0#
0)
13
#70000
0!
1#
1)
03
#75000
1!
0#
0)
13
#80000
0!
1#
1)
03
#85000
1!
0#
0)
13
#90000
0!
1#
1)
03
#95000
1!
0#
0)
13
#100000
0!
1"
1#
1)
03
14
07
#105000
1!
0#
b100 &
0)
13
b100 8
b1000 9
b1000 :
b1000000100 ;
b0 V
b100 W
#110000
0!
1#
b101010000000100011 (
1)
b1111 +
b1000000000 ,
03
b101010000000100011 5
b100 ;
b101010000000100011 <
b100011 >
b0 ?
b10 @
b101 A
b0 C
0D
1E
1F
b1 G
b1000000000 M
b0 O
b0 P
b1000000000 Q
0R
b1000000000 S
b1000000000 U
b0 V
0Y
b1 Z
1[
1\
b0 ]
b0 ^
b0 _
0`
0a
b0 b
b1000000000 c
#115000
1!
0#
b1000 &
0)
13
b1000 8
b1100 9
b1100 :
b1000 ;
b0 V
b1000 W
#120000
0!
1#
b100000000000000010000010011 (
1)
b0 +
b1000000 ,
03
b100000000000000010000010011 5
b1001000 ;
b100000000000000010000010011 <
b10011 >
b1000 ?
b0 @
b0 A
b10 C
1D
1E
0F
b0 G
b0 M
b1000000 O
b1000000 P
b1000000 Q
0R
b1000000 S
0T
b1000000 U
b0 V
1Y
b0 Z
1[
0\
b0 ]
b10 ^
b0 _
0`
0a
b1000000 b
b1000000 c
#125000
1!
0#
b1100 &
0)
13
b1100 8
b10000 9
b10000 :
b1001100 ;
b0 M
b0 N
b0 V
b1100 W
#130000
0!
1#
b100000000010010010011 (
1)
b1 ,
bx -
b10010000101010011010100100100 .
03
b100000000010010010011 5
b10010000101010011010100100100 6
b1101 ;
b100000000010010010011 <
b10010000101010011010100100100 =
b1001 ?
b1 B
b0 C
bx N
b1 O
b1 P
b1 Q
0R
b1 S
b1 U
b0 V
b0 _
b1 b
b1 c
#135000
1!
0#
b10000 &
0)
13
b10000 8
b10100 9
b10100 :
b10001 ;
b0 M
bx N
b0 V
b10000 W
#140000
0!
1#
b10000000000000001100010011 (
1)
b100000 ,
b0 -
bx .
03
b10000000000000001100010011 5
bx 6
b110000 ;
b10000000000000001100010011 <
bx =
b110 ?
b0 B
b1 C
b0 N
b100000 O
b100000 P
b100000 Q
0R
b100000 S
b100000 U
b0 V
b0 _
b100000 b
b100000 c
#145000
1!
0#
b10100 &
0)
13
b10100 8
b11000 9
b11000 :
b110100 ;
b0 M
b0 N
b0 V
b10100 W
#150000
0!
1#
b11001001010001110110011 (
1)
b1 ,
b100000 -
03
b11001001010001110110011 5
b11010 ;
b11001001010001110110011 <
b110011 >
b111 ?
b10 @
b1001 A
b110 B
b0 C
0E
b11 J
b1 M
b100000 N
b110 O
b100000 P
b1 Q
0R
b1 S
b1 U
b0 V
1Y
b0 Z
0[
0\
b0 ]
b1 ^
b11 _
0`
0a
b110 b
b1 c
#155000
1!
0#
b11000 &
0)
13
b11000 8
b11100 9
b11100 :
b11110 ;
b1 M
b100000 N
b0 V
b11000 W
#160000
0!
1#
b110000000111000010001100011 (
1)
b1 ,
b0 -
03
b110000000111000010001100011 5
b11100 9
b10000000 ;
b110000000111000010001100011 <
b1100011 >
b1000 ?
b0 @
b111 A
b0 B
b11 C
0D
b10 G
b1 J
1K
b1 M
b0 N
b1101000 O
b0 P
b1 Q
0R
b1 S
0T
b1 U
b0 V
0Y
b10 Z
0[
0\
b0 ]
b11 ^
b1 _
1`
0a
b1101000 b
b1 c
#165000
1!
0#
b11100 &
0)
13
b11100 8
b100000 9
b100000 :
b10000100 ;
b0 V
b11100 W
#170000
0!
1#
b1001001001111000010011 (
1)
b100 ,
bx -
03
b1001001001111000010011 5
b100000 9
b11110 ;
b1001001001111000010011 <
b10011 >
b11100 ?
b1 @
b1001 A
b10 B
b0 C
1D
1E
b0 G
b10 J
0K
b1 M
bx N
b10 O
b10 P
b100 Q
0R
b100 S
0T
b100 U
b0 V
1Y
b0 Z
1[
0\
b0 ]
b10 ^
b10 _
0`
0a
b10 b
b100 c
#175000
1!
0#
b100000 &
0)
13
b100000 8
b100100 9
b100100 :
b100010 ;
b1 M
bx N
b0 V
b100000 W
#180000
0!
1#
b1110001000000111010110011 (
1)
b1000100 ,
b100 -
03
b1110001000000111010110011 5
b111100 ;
b1110001000000111010110011 <
b110011 >
b11101 ?
b0 @
b1000 A
b11100 B
0E
b0 J
b1000000 M
b100 N
b11100 O
b100 P
b1000100 Q
0R
b1000100 S
b1000100 U
b0 V
1Y
b0 Z
0[
0\
b0 ]
b1 ^
b0 _
0`
0a
b11100 b
b1000100 c
#185000
1!
0#
b100100 &
0)
13
b100100 8
b101000 9
b101000 :
b1000000 ;
b1000000 M
b100 N
b0 V
b100100 W
#190000
0!
1#
b11101010100100000011 (
1)
b0 -
b11000000100010010101111010000001 .
03
b11101010100100000011 5
b11000000100010010101111010000001 6
b100100 ;
b11101010100100000011 <
b11000000100010010101111010000001 =
b11 >
b10010 ?
b10 @
b11101 A
b0 B
1E
b1 H
b1000100 M
b0 N
b0 O
b0 P
b11000000100010010101111010000001 S
b11000000100010010101111010000001 U
b0 V
1Y
b0 Z
1[
0\
b1 ]
b0 ^
b0 _
0`
0a
b0 b
b1000100 c
#195000
1!
0#
b101000 &
0)
13
b101000 8
b101100 9
b101100 :
b101000 ;
b1000100 M
b0 N
b0 V
b101000 W
#200000
0!
1#
b11111111111101001000100110010011 (
1)
b0 ,
bx -
03
b11111111111101001000100110010011 5
b100111 ;
b11111111111101001000100110010011 <
b10011 >
b10011 ?
b0 @
b1001 A
b11111 B
b1111111 C
1E
b0 H
b1 M
bx N
b11111111111111111111111111111111 O
b11111111111111111111111111111111 P
b0 Q
1R
b0 S
0T
b0 U
b0 V
1Y
b0 Z
1[
0\
b0 ]
b10 ^
b0 _
0`
0a
b11111111111111111111111111111111 b
b0 c
#205000
1!
0#
b101100 &
0)
13
b101100 8
b110000 9
b110000 :
b101011 ;
b1 M
bx N
b0 V
b101100 W
#210000
0!
1#
b10011010111100110011 (
1)
b0 ,
b0 -
bx .
03
b10011010111100110011 5
bx 6
b101100 ;
b10011010111100110011 <
bx =
b110011 >
b11110 ?
b10 @
b10011 A
b0 B
b0 C
0E
b11 J
b0 M
b0 N
b0 O
b0 P
b0 Q
1R
b0 S
0T
b0 U
b0 V
1Y
b0 Z
0[
0\
b0 ]
b1 ^
b11 _
0`
0a
b0 b
b0 c
#215000
1!
0#
b110000 &
0)
13
b110000 8
b110100 9
b110100 :
b110000 ;
b0 M
b0 N
b0 V
b110000 W
#220000
0!
1#
b11110000010001100011 (
1)
03
b11110000010001100011 5
b111000 9
b111000 ;
b11110000010001100011 <
b1100011 >
b1000 ?
b0 @
b11110 A
0D
b10 G
b1 J
1K
b0 M
b1000 O
b0 P
1T
b0 V
0Y
b10 Z
0[
0\
b0 ]
b11 ^
b1 _
1`
0a
b1000 b
b0 c
#225000
1!
0#
b111000 &
0)
13
b111000 8
b1000000 9
b111100 :
b1000000 ;
b0 V
b111000 W
#230000
0!
1#
b1010011001111110010011 (
1)
b0 ,
bx -
03
b1010011001111110010011 5
b111100 9
b111010 ;
b1010011001111110010011 <
b10011 >
b11111 ?
b1 @
b10011 A
b10 B
1D
1E
b0 G
b10 J
0K
b0 M
bx N
b10 O
b10 P
b0 Q
1R
b0 S
0T
b0 U
b0 V
1Y
b0 Z
1[
0\
b0 ]
b10 ^
b10 _
0`
0a
b10 b
b0 c
#235000
1!
0#
b111100 &
0)
13
b111100 8
b1000000 9
b1000000 :
b111110 ;
b0 M
bx N
b0 V
b111100 W
#240000
0!
1#
b1111101000000010100110011 (
1)
b1000000 ,
b0 -
03
b1111101000000010100110011 5
b1011011 ;
b1111101000000010100110011 <
b110011 >
b1010 ?
b0 @
b1000 A
b11111 B
0E
b0 J
b1000000 M
b0 N
b11111 O
b0 P
b1000000 Q
0R
b1000000 S
0T
b1000000 U
b0 V
1Y
b0 Z
0[
0\
b0 ]
b1 ^
b0 _
0`
0a
b11111 b
b1000000 c
#245000
1!
0#
b1000000 &
0)
13
b1000000 8
b1000100 9
b1000100 :
b1011111 ;
b1000000 M
b0 N
b0 V
b1000000 W
#250000
0!
1#
b1010010010110000011 (
1)
b10010000101010011010100100100 .
03
b1010010010110000011 5
b10010000101010011010100100100 6
b1000000 ;
b1010010010110000011 <
b10010000101010011010100100100 =
b11 >
b1011 ?
b10 @
b1010 A
b0 B
1E
b1 H
b1000000 M
b0 N
b0 O
b0 P
b10010000101010011010100100100 S
b10010000101010011010100100100 U
b0 V
1Y
b0 Z
1[
0\
b1 ]
b0 ^
b0 _
0`
0a
b0 b
#255000
1!
0#
b1000100 &
0)
13
b1000100 8
b1001000 9
b1001000 :
b1000100 ;
b1000000 M
b0 N
b0 V
b1000100 W
#260000
0!
1#
b101110010010011000110011 (
1)
b1 ,
b10010000101010011010100100100 -
03
b101110010010011000110011 5
b1001111 ;
b101110010010011000110011 <
b110011 >
b1100 ?
b10010 A
b1011 B
0E
b0 H
b11 J
b11000000100010010101111010000001 M
b10010000101010011010100100100 N
b1011 O
b10010000101010011010100100100 P
b1 Q
0R
b1 S
b1 U
b0 V
1Y
b0 Z
0[
0\
b0 ]
b1 ^
b11 _
0`
0a
b1011 b
b1 c
#265000
1!
0#
b1001000 &
0)
13
b1001000 8
b1001100 9
b1001100 :
b1010011 ;
b11000000100010010101111010000001 M
b10010000101010011010100100100 N
b0 V
b1001000 W
#270000
0!
1#
b10000001100000000001100011 (
1)
b1 ,
b0 -
bx .
03
b10000001100000000001100011 5
bx 6
b1001100 9
b1101000 ;
b10000001100000000001100011 <
bx =
b1100011 >
b0 ?
b0 @
b1100 A
b0 B
b1 C
0D
b10 G
b1 J
1K
b1 M
b0 N
b100000 O
b0 P
b1 Q
0R
b1 S
0T
b1 U
b0 V
0Y
b10 Z
0[
0\
b0 ]
b11 ^
b1 _
1`
0a
b100000 b
b1 c
#275000
1!
0#
b1001100 &
0)
13
b1001100 8
b1010000 9
b1010000 :
b1101100 ;
b0 V
b1001100 W
